<?xml version="1.0" encoding="utf-8" standalone="no"?>
<!DOCTYPE business:PatentDocumentAndRelated SYSTEM "/DTDS/ExternalStandards/ipphdb-entities.dtd"[]>
<business:PatentDocumentAndRelated xmlns:base="http://www.sipo.gov.cn/XMLSchema/base" xmlns:business="http://www.sipo.gov.cn/XMLSchema/business" xmlns:m="http://www.w3.org/1998/Math/MathML" xmlns:tbl="http://oasis-open.org/specs/soextblx" xmlns:xsi="http://www.w3.org/2001/XMLSchema-instance" xsi:schemaLocation="http://www.sipo.gov.cn/XMLSchema/business /DTDS/PatentDocument/Elements/OtherElements.xsd" xsdVersion="V2.2.1" file="JP102015000211824JP00020161272660AFULJA20160711JP00B.XML" dateProduced="20160812" status="C" lang="ja" country="JP" docNumber="2016127266" kind="A" datePublication="20160711">
  <business:BibliographicData lang="ja" country="JP">
    <business:PublicationReference dataFormat="standard" sequence="1">
      <base:DocumentID>
        <base:WIPOST3Code>JP</base:WIPOST3Code>
        <base:DocNumber>2016127266</base:DocNumber>
        <base:Kind>A</base:Kind>
        <base:Date>20160711</base:Date>
      </base:DocumentID>
    </business:PublicationReference>
    <business:PublicationReference dataFormat="original" sourceDB="JP" sequence="1">
      <base:DocumentID>
        <base:WIPOST3Code>JP</base:WIPOST3Code>
        <base:DocNumber>2016127266</base:DocNumber>
        <base:Kind>A</base:Kind>
        <base:Date>20160711</base:Date>
      </base:DocumentID>
    </business:PublicationReference>
    <business:PlainLanguageDesignation lang="ja">公開特許公報(A)</business:PlainLanguageDesignation>
    <business:ApplicationReference applType="10" dataFormat="standard" sequence="1">
      <base:DocumentID>
        <base:WIPOST3Code>JP</base:WIPOST3Code>
        <base:DocNumber>102015000211824</base:DocNumber>
        <base:Date>20151028</base:Date>
      </base:DocumentID>
    </business:ApplicationReference>
    <business:ApplicationReference applType="10" dataFormat="original" sequence="1" sourceDB="JP">
      <base:DocumentID>
        <base:WIPOST3Code>JP</base:WIPOST3Code>
        <base:DocNumber>2015211824</base:DocNumber>
        <base:Date>20151028</base:Date>
      </base:DocumentID>
    </business:ApplicationReference>
    <business:PriorityDetails>
      <business:Priority kind="national" dataFormat="standard" sequence="1">
        <base:WIPOST3Code>JP</base:WIPOST3Code>
        <base:DocNumber>002014000263983</base:DocNumber>
        <base:Date>20141226</base:Date>
      </business:Priority>
      <business:Priority kind="national" dataFormat="original" sourceDB="JP" sequence="1">
        <base:WIPOST3Code>JP</base:WIPOST3Code>
        <base:DocNumber>2014263983</base:DocNumber>
        <base:Date>20141226</base:Date>
      </business:Priority>
    </business:PriorityDetails>
    <business:ClassificationIPCRDetails>
      <business:ClassificationIPCR sequence="1">
        <business:IPCVersionDate>20060101</business:IPCVersionDate>
        <business:ClassificationLevel>A</business:ClassificationLevel>
        <business:Section>H</business:Section>
        <business:MainClass>01</business:MainClass>
        <business:Subclass>F</business:Subclass>
        <business:MainGroup>7</business:MainGroup>
        <business:Subgroup>16</business:Subgroup>
        <business:SymbolPosition>F</business:SymbolPosition>
        <business:ClassificationValue>I</business:ClassificationValue>
        <base:ActionDate>
          <base:Date>20160613</base:Date>
        </base:ActionDate>
        <business:GeneratingOffice>
          <base:WIPOST3Code>JP</base:WIPOST3Code>
        </business:GeneratingOffice>
        <business:ClassificationStatus>B</business:ClassificationStatus>
        <business:ClassificationDataSource>H</business:ClassificationDataSource>
        <base:Text>H01F   7/16        20060101AFI20160613BHJP        </base:Text>
      </business:ClassificationIPCR>
      <business:ClassificationIPCR sequence="2">
        <business:IPCVersionDate>20060101</business:IPCVersionDate>
        <business:ClassificationLevel>A</business:ClassificationLevel>
        <business:Section>H</business:Section>
        <business:MainClass>01</business:MainClass>
        <business:Subclass>F</business:Subclass>
        <business:MainGroup>7</business:MainGroup>
        <business:Subgroup>121</business:Subgroup>
        <business:SymbolPosition>L</business:SymbolPosition>
        <business:ClassificationValue>I</business:ClassificationValue>
        <base:ActionDate>
          <base:Date>20160613</base:Date>
        </base:ActionDate>
        <business:GeneratingOffice>
          <base:WIPOST3Code>JP</base:WIPOST3Code>
        </business:GeneratingOffice>
        <business:ClassificationStatus>B</business:ClassificationStatus>
        <business:ClassificationDataSource>H</business:ClassificationDataSource>
        <base:Text>H01F   7/121       20060101ALI20160613BHJP        </base:Text>
      </business:ClassificationIPCR>
      <business:ClassificationIPCR sequence="3">
        <business:IPCVersionDate>20060101</business:IPCVersionDate>
        <business:ClassificationLevel>A</business:ClassificationLevel>
        <business:Section>F</business:Section>
        <business:MainClass>16</business:MainClass>
        <business:Subclass>K</business:Subclass>
        <business:MainGroup>31</business:MainGroup>
        <business:Subgroup>06</business:Subgroup>
        <business:SymbolPosition>L</business:SymbolPosition>
        <business:ClassificationValue>I</business:ClassificationValue>
        <base:ActionDate>
          <base:Date>20160613</base:Date>
        </base:ActionDate>
        <business:GeneratingOffice>
          <base:WIPOST3Code>JP</base:WIPOST3Code>
        </business:GeneratingOffice>
        <business:ClassificationStatus>B</business:ClassificationStatus>
        <business:ClassificationDataSource>H</business:ClassificationDataSource>
        <base:Text>F16K  31/06        20060101ALI20160613BHJP        </base:Text>
      </business:ClassificationIPCR>
    </business:ClassificationIPCRDetails>
    <business:JPClassification>
      <business:FI type="main">H01F7/16 P</business:FI>
      <business:FI type="secondary">H01F7/16 F</business:FI>
      <business:FI type="secondary">F16K31/06 305J</business:FI>
      <business:FClass>
        <business:FTerm>3H106DA23</business:FTerm>
      </business:FClass>
      <business:FClass>
        <business:FTerm>3H106DB02</business:FTerm>
      </business:FClass>
      <business:FClass>
        <business:FTerm>3H106DC09</business:FTerm>
      </business:FClass>
      <business:FClass>
        <business:FTerm>3H106DD05</business:FTerm>
      </business:FClass>
      <business:FClass>
        <business:FTerm>3H106EE24</business:FTerm>
      </business:FClass>
      <business:FClass>
        <business:FTerm>3H106GA22</business:FTerm>
      </business:FClass>
      <business:FClass>
        <business:FTerm>5E048AA10</business:FTerm>
      </business:FClass>
      <business:FClass>
        <business:FTerm>5E048AD02</business:FTerm>
      </business:FClass>
      <business:FClass>
        <business:Theme>3H106</business:Theme>
      </business:FClass>
      <business:FClass>
        <business:Theme>5E048</business:Theme>
      </business:FClass>
    </business:JPClassification>
    <business:InventionTitle lang="ja" dataFormat="original" sourceDB="JP">電磁アクチュエータ</business:InventionTitle>
    <business:Parties>
      <business:ApplicantDetails>
        <business:Applicant sequence="1" dataFormat="original" sourceDB="JP">
          <base:AddressBook lang="ja">
            <base:Name>株式会社デンソー</base:Name>
            <base:RegisteredNumber>000004260</base:RegisteredNumber>
            <base:Address>
              <base:AddressLine>0</base:AddressLine>
              <base:AddressMailCode>0</base:AddressMailCode>
              <base:PostBox>0</base:PostBox>
              <base:AddressRoom>0</base:AddressRoom>
              <base:AddressFloor>0</base:AddressFloor>
              <base:AddressBuilding>0</base:AddressBuilding>
              <base:Street>0</base:Street>
              <base:AddressCity>0</base:AddressCity>
              <base:County>0</base:County>
              <base:City>0</base:City>
              <base:Province>0</base:Province>
              <base:PostCode>0</base:PostCode>
              <base:WIPOST3Code>XP</base:WIPOST3Code>
              <base:Text>愛知県刈谷市昭和町１丁目１番地</base:Text>
            </base:Address>
          </base:AddressBook>
          <business:OrganizationCode createDate="00000000" creator="00">0000000000</business:OrganizationCode>
        </business:Applicant>
      </business:ApplicantDetails>
      <business:InventorDetails>
        <business:Inventor sequence="1" dataFormat="original" sourceDB="JP">
          <base:AddressBook lang="ja">
            <base:Name>長坂  進介</base:Name>
            <base:Address>
              <base:AddressLine>0</base:AddressLine>
              <base:AddressMailCode>0</base:AddressMailCode>
              <base:PostBox>0</base:PostBox>
              <base:AddressRoom>0</base:AddressRoom>
              <base:AddressFloor>0</base:AddressFloor>
              <base:AddressBuilding>0</base:AddressBuilding>
              <base:Street>0</base:Street>
              <base:AddressCity>0</base:AddressCity>
              <base:County>0</base:County>
              <base:City>0</base:City>
              <base:Province>0</base:Province>
              <base:PostCode>0</base:PostCode>
              <base:WIPOST3Code>XP</base:WIPOST3Code>
              <base:Text>愛知県刈谷市昭和町１丁目１番地  株式会社デンソー内</base:Text>
            </base:Address>
          </base:AddressBook>
        </business:Inventor>
      </business:InventorDetails>
      <business:AgentDetails>
        <business:CustomerNumber>00000</business:CustomerNumber>
        <business:Agent sequence="1" dataFormat="original" sourceDB="JP" repType="agent">
          <base:AddressBook lang="ja">
            <base:Name>服部  雅紀</base:Name>
            <base:RegisteredNumber>100093779</base:RegisteredNumber>
          </base:AddressBook>
        </business:Agent>
      </business:AgentDetails>
    </business:Parties>
    <business:SpecificBibliographicData>
      <business:OriginalKindCode>A</business:OriginalKindCode>
    </business:SpecificBibliographicData>
    <business:StatisticalInformation>
      <business:ClaimsCount>7</business:ClaimsCount>
      <base:TotalPageCount>16</base:TotalPageCount>
    </business:StatisticalInformation>
  </business:BibliographicData>
  <business:Abstract dataFormat="original" lang="ja" sourceDB="JP">
    <base:Paragraphs>【課題】ロッドと支持部との摩擦力低減と、ロッド先端の径方向への振れ量低減との両立を図った電磁アクチュエータを提供する。【解決手段】電磁駆動部ＭＤにロッド１７が挿通している通孔３３が形成され、ロット１７は、通孔３３と摺動する外壁面４２を有する。最大突出位置に位置するロッド１７の外壁面４２から通孔３３の内壁面３４までのクリアランスＣＢは、最大引込位置に位置するロッド１７の外壁面４２から内壁面３４までのクリアランスＣＡよりも小さい。これにより、引込時クリアランスが比較的大きいことによって、ロッド１７と支持筒部３２との摩擦力を低減可能である。また、突出時クリアランスが比較的小さいことによって、ロッド１７の先端４４の径方向への振れ量を低減可能である。つまり、ロッドと支持部との摩擦力低減と、ロッド先端の径方向への振れ量低減との両立を図ることができる。【選択図】図４</base:Paragraphs>
    <business:AbstractFigure>
      <base:Figure num="0001">
        <base:Image id="000002" he="97" wi="66" file="2016127266_000002.TIF" imgFormat="TIFF" imgContent="drawing" />
      </base:Figure>
    </business:AbstractFigure>
  </business:Abstract>
  <business:Description dataFormat="original" sourceDB="JP">
    <business:TechnicalField>
      <base:Paragraphs num="0001">
  本発明は、電磁アクチュエータに関する。
</base:Paragraphs>
    </business:TechnicalField>
    <business:BackgroundArt>
      <base:Paragraphs num="0002">
  コイルを通電するとき生じる磁力によりプランジャを軸方向へ相対移動し、プランジャと一体のロッドによって外部機器を操作可能な電磁アクチュエータが知られている。例えば特許文献１の電磁アクチュエータは、エンジンのバルブタイミング調整装置の油圧制御弁を操作する用途に用いられている。
  特許文献１では、ロッドは、プランジャから軸方向へ突き出すように設けられている。ロッドの外周面は軸心に対して平行である。また、ヨークは、ロッドが挿通する通孔を有する支持部を形成している。
</base:Paragraphs>
    </business:BackgroundArt>
    <business:CitationList>
      <business:PatentDocumentation>
        <base:Paragraphs num="0003">
          <business:ApplicationCitation num="0001">
            <base:Text>特開２０１４－１２０７１４号公報</base:Text>
          </business:ApplicationCitation>
        </base:Paragraphs>
      </business:PatentDocumentation>
    </business:CitationList>
    <business:InventionSummary>
      <business:TechnicalProblem>
        <base:Paragraphs num="0004">
  ところで、ロッドは、軸方向へ移動するとき支持部の通孔の内壁面と摺動する。このときの摩擦力が大きいと、ロッドおよび支持部の摩耗が増えるとともに、ロッドが移動不能となる所謂こじりが発生するおそれがある。この問題の対策としては、ロッドと通孔の内壁面とのクリアランスを大きくすることが考えられる。
</base:Paragraphs>
        <base:Paragraphs num="0005">
  一方、ロッドは、コイルの通電量が大きくなって磁力が大きくなるほど、ロッドが支持部から突き出す長さが長くなるとともに、プランジャに対して径方向にかかる力（サイドフォース）が大きくなる。そのため、ロッドが支持部から突き出す長さが長いときにロッド先端の径方向への振れ量が大きくなるという問題がある。この問題の対策としては、ロッドと通孔の内壁面とのクリアランスを小さくすることが考えられる。
</base:Paragraphs>
        <base:Paragraphs num="0006">
  したがって、上述の２つの対策は互いに相容れない。つまり、ロッドと支持部との摩擦力を小さくするためにクリアランスを大きくすると、ロッド先端の径方向への振れ量が大きくなってしまう。また、ロッド先端の径方向への振れ量を小さくするためにクリアランスを小さくすると、ロッドと支持部との摩擦力が大きくなってしまう。
</base:Paragraphs>
        <base:Paragraphs num="0007">
  本発明は、上述の点に鑑みてなされたものであり、その目的は、ロッドと支持部との摩擦力低減と、ロッド先端の径方向への振れ量低減との両立を図った電磁アクチュエータを提供することである。
</base:Paragraphs>
      </business:TechnicalProblem>
      <business:TechnicalSolution>
        <base:Paragraphs num="0008">
  本発明による電磁アクチュエータは、可動部（１１）、電磁駆動部（ＭＤ）およびロッド（１７）を備える。可動部は、所定の直線方向へ往復移動可能である。電磁駆動部は、環状のコイル（１２）を有し、コイルが通電されると、可動部を前記直線方向へ移動させる磁力を発生可能である。ロッドは、可動部から前記直線方向へ突き出すように形成され、前記直線方向の一方側に位置する最大引込位置から前記直線方向の他方側に位置する最大突出位置まで可動部と共に移動可能である。電磁駆動部にロッドが挿通している通孔（３３）を有する。ロッドは、通孔と摺動する外壁面（４２、５０、６０、７０）を有する。
</base:Paragraphs>
        <base:Paragraphs num="0009">
  最大突出位置に位置するロッドの外壁面から通孔の内壁面（３４）までクリアランス（ＣＢ）は、最大引込位置に位置するロッドの外壁面から内壁面までのクリアランス（ＣＡ）よりも小さい。
</base:Paragraphs>
        <base:Paragraphs num="0010">
  このように構成すれば、ロッドが引き込み側に位置するときのロッドと通孔の内壁面とのクリアランス（引込時クリアランス）を比較的大きくしつつ、ロッドが突き出し側に位置するときのロッドと通孔の内壁面とのクリアランス（突出時クリアランス）を比較的小さくすることができる。したがって、引込時クリアランスが比較的大きいことによって、ロッドと支持部との摩擦力を低減可能である。また、突出時クリアランスが比較的小さいことによって、ロッド先端の径方向への振れ量を低減可能である。つまり、ロッドと支持部との摩擦力低減と、ロッド先端の径方向への振れ量低減との両立を図ることができる。
</base:Paragraphs>
      </business:TechnicalSolution>
    </business:InventionSummary>
    <business:DrawingsDescription>
      <base:Paragraphs num="0011">
        <base:FigureReference num="0001">本発明の第１実施形態による電磁アクチュエータと、これが適用されたエンジンのバルブタイミング調整装置および油圧制御弁とを説明する断面図である。</base:FigureReference>
        <base:FigureReference num="0002">図１の電磁アクチュエータの断面図であって、ロッドが最大引込位置に位置している状態を示す図である。</base:FigureReference>
        <base:FigureReference num="0003">図１の電磁アクチュエータの断面図であって、ロッドが最大突出位置に位置している状態を示す図である。</base:FigureReference>
        <base:FigureReference num="0004">図２のＩＶ部分を拡大して模式的に示す図である。</base:FigureReference>
        <base:FigureReference num="0005">図３のＶ部分を拡大して模式的に示す図である。</base:FigureReference>
        <base:FigureReference num="0006">図１の電磁アクチュエータにおけるロッドのストローク量とロッドに作用する摩擦力との関係、および、ロッドのストローク量とロッド先端の径方向振れ量との関係を示す図である。</base:FigureReference>
        <base:FigureReference num="0007">図５の状態からロッドが径方向へ振れた状態を示す図である。</base:FigureReference>
        <base:FigureReference num="0008">本発明の第２実施形態による電磁アクチュエータのロッドおよびカバーを示す模式図である。</base:FigureReference>
        <base:FigureReference num="0009">本発明の第３実施形態による電磁アクチュエータのロッドおよびカバーを示す模式図である。</base:FigureReference>
        <base:FigureReference num="0010">本発明の第４実施形態による電磁アクチュエータのロッドおよびカバーを示す模式図である。</base:FigureReference>
        <base:FigureReference num="0011">本発明の他の実施形態による電磁アクチュエータのロッドおよびカバーを示す模式図である。</base:FigureReference>
        <base:FigureReference num="0012">本発明の他の実施形態による電磁アクチュエータのロッドおよびカバーを示す模式図である。</base:FigureReference>
        <base:FigureReference num="0013">本発明の他の実施形態による電磁アクチュエータのロッドおよびカバーを示す模式図である。</base:FigureReference>
        <base:FigureReference num="0014">本発明の他の実施形態による電磁アクチュエータのロッドおよびカバーを示す模式図である。</base:FigureReference>
        <base:FigureReference num="0015">本発明の他の実施形態による電磁アクチュエータのロッドおよびカバーを示す模式図である。</base:FigureReference>
        <base:FigureReference num="0016">本発明の他の実施形態による電磁アクチュエータのロッドおよびカバーを示す模式図である。</base:FigureReference>
        <base:FigureReference num="0017">本発明の他の実施形態による電磁アクチュエータのロッドおよびカバーを示す模式図である。</base:FigureReference>
        <base:FigureReference num="0018">本発明の他の実施形態による電磁アクチュエータのロッドおよびカバーを示す模式図である。</base:FigureReference>
        <base:FigureReference num="0019">第１比較形態による電磁アクチュエータのロッドおよびカバーを示す模式図である。</base:FigureReference>
        <base:FigureReference num="0020">図１９の電磁アクチュエータにおけるロッドのストローク量とロッドに作用する摩擦力との関係、および、ロッドのストローク量とロッド先端の径方向振れ量との関係を示す図である。</base:FigureReference>
        <base:FigureReference num="0021">第２比較形態による電磁アクチュエータのロッド、および、カバーを示す模式図である。</base:FigureReference>
        <base:FigureReference num="0022">図２１の電磁アクチュエータにおけるロッドのストローク量とロッドに作用する摩擦力との関係、および、ロッドのストローク量とロッド先端の径方向振れ量との関係を示す図である。</base:FigureReference>
      </base:Paragraphs>
    </business:DrawingsDescription>
    <business:EmbodimentsDescription>
      <base:Paragraphs num="0012">
  以下、本発明の複数の実施形態を図面に基づき説明する。実施形態同士で実質的に同一の構成には同一の符号を付して説明を省略する。
  ［第１実施形態］
  本発明の第１実施形態による電磁アクチュエータは、図１に示すエンジンのバルブタイミング調整システム８０に適用されている。バルブタイミング調整システム８０は、バルブタイミング調整装置８１および油圧制御弁８２を備えている。
</base:Paragraphs>
      <base:Paragraphs num="0013">
  バルブタイミング調整装置８１は、エンジンのクランク軸と同期して回転するハウジング８４と、エンジンのカム軸８５と一体に回転するベーンロータ８６とを備え、ハウジング８４とベーンロータ８６との相対回転位相を変更することにより、エンジンの吸気弁または排気弁のバルブタイミングを調整可能である。ベーンロータ８６は、ハウジング８４内の油圧室（進角室、遅角室）の油圧の大きさに応じて当該ハウジング８４に対して相対回転する。油圧室の油圧は、ベーンロータ８６の中心部に設けられている油圧制御弁８２により調圧される。
</base:Paragraphs>
      <base:Paragraphs num="0014">
  油圧制御弁８２は、複数のポート８７を有するスリーブ８８と、スリーブ８８内で軸方向へ移動可能なスプール８９とを備えるスプール弁であり、スプール８９の軸方向位置を変化させることにより各ポート８７を選択的に開閉して、ハウジング８４内の油圧室に作動油を供給するための油路を切り替える。電磁アクチュエータ１０は、油圧制御弁８２のスプール８９の軸方向位置を変化させるために用いられる。
</base:Paragraphs>
      <base:Paragraphs num="0015">
  （基本構成）
  先ず、電磁アクチュエータ１０の基本構成を図１～図３に基づき説明する。
  電磁アクチュエータ１０は、電磁駆動部ＭＤ、ハウジング１５、ブラケット１６、および、「出力軸部」としてのロッド１７を備える。電磁駆動部ＭＤは、「可動部」としてのプランジャ１１、コイル１２、ヨーク１３、コアステータ１４、および、カバー１８を有する。
電磁アクチュエータ１０は、ロッド１７を軸方向の一方側の最大引込位置から軸方向の他方側の最大突出位置までの間で移動させることにより、油圧制御弁８２のスプール８９の軸方向位置を変化させる。
</base:Paragraphs>
      <base:Paragraphs num="0016">
  以下、ロッド１７の軸心ＡＸと平行な方向を単に「軸方向」という。また、「軸方向の一方」とはロッド１７に対してスプール８９とは反対側のことを意味し、「軸方向の他方」とはロッド１７に対してスプール８９側のことを意味する。
</base:Paragraphs>
      <base:Paragraphs num="0017">
  プランジャ１１は、中空筒状であり、磁性材料で作られている。プランジャ１１は、軸心ＡＸ上に設けられており、軸方向へ往復移動可能である。軸方向は、特許請求の範囲に記載の「直線方向」に相当する。
</base:Paragraphs>
      <base:Paragraphs num="0018">
  コイル１２は、樹脂製かつ筒状のボビン１９の外側に巻かれた巻線から構成されている。ボビン１９は、軸心ＡＸ上であってプランジャ１１の外側に設けられている。外部の電源からハウジング１５のコネクタ部２０のターミナル２１を経由して通電されることにより、コイル１２は磁界を発生する。
</base:Paragraphs>
      <base:Paragraphs num="0019">
  ヨーク１３は、軸心ＡＸに沿う断面においてコイル１２を取り囲むように設けられており、磁性材料で作られている。本実施形態では、ヨーク１３は第１ヨーク部材２２および第２ヨーク部材２３から構成されている。第１ヨーク部材２２は、コイル１２の内側に位置する第１内側筒部２４を有する。第２ヨーク部材２３は、コイル１２の内側に位置し、且つ、第１内側筒部２４との間に磁気ギャップ２５を隔てて配置された第２内側筒部２６を有する。第１ヨーク部材２２と第２ヨーク部材２３とは、コイル１２の外側で互いに接続されている。
</base:Paragraphs>
      <base:Paragraphs num="0020">
  コアステータ１４は、プランジャ１１の内側に位置する軸部２７と、軸部２７のうち軸方向の一方側の端部から第１ヨーク部材２２まで突き出すフランジ部２８と、を有する。
  ハウジング１５は、樹脂製であり、ヨーク１３の一部の外側を覆うように設けられている。
  ブラケット１６は、ハウジング１５から外側へ突き出すように形成されており、締結部材９０が挿入可能な取り付け孔２９を有する。
</base:Paragraphs>
      <base:Paragraphs num="0021">
  ロッド１７は、プランジャ１１から軸方向の他方へ突き出すように設けられており、スプール８９を軸方向へ押圧可能である。ロッド１７は、図１、図２に示すように軸方向の一方側に位置する最大引込位置から、図３に示すように軸方向の他方側に位置する最大突出位置まで、プランジャ１１と共に移動可能である。本実施形態では、最大引込位置は、ロッド１７がコアステータ１４に当接する位置である。最大突出位置は、ロッド１７に押されたスプール８９がスリーブ８８の内壁に当接する位置である。電磁アクチュエータ１０がエンジンから取り外された状態であれば、ロッド１７は、最大突出位置よりもさらに軸方向の他方へ移動可能である。
</base:Paragraphs>
      <base:Paragraphs num="0022">
  ロッド１７が最大引込位置に位置するとき、図２に示すように、プランジャ１１は第１内側筒部２４の内側に位置する。ロッド１７が最大突出位置に位置するとき、図３に示すように、プランジャ１１は第１内側筒部２４と第２内側筒部２６とに跨るように位置する。
</base:Paragraphs>
      <base:Paragraphs num="0023">
  カバー１８は、第２内側筒部２６のうち、軸方向の他方側の端部に嵌合されて固定されている嵌合筒部３０と、嵌合筒部３０から径方向内側へ突き出す環状板部３１と、環状板部３１の内周部から軸方向の他方へ突き出す支持筒部３２と、を有する。支持筒部３２は、ロッド１７が挿通している通孔３３を有する。支持筒部３２は、例えばプランジャ１１に径方向の力がかかるとき等に径方向へ振れるロッド１７を支持可能である。
</base:Paragraphs>
      <base:Paragraphs num="0024">
  このように構成された電磁アクチュエータ１０では、コイル１２が非通電のとき、プランジャ１１およびロッド１７は、油圧制御弁８２のスプリング９１によりスプール８９を介して軸方向の一方へ付勢され、最大引込位置に位置させられる。
</base:Paragraphs>
      <base:Paragraphs num="0025">
  一方、コイル１２が通電されると、コイル１２の周りに磁界が発生し、ヨーク１３およびプランジャ１１により磁気回路が形成される。このとき、磁束が流れにくい磁気ギャップ２５をバイパスするようにプランジャ１１を移動させようと、プランジャ１１には軸方向の他方へ向かう磁力が作用する。コイル１２の通電量が大きいほど、すなわち磁気回路を流れる磁束が多いほど、上記磁力は大きくなる。プランジャ１１、ロッド１７およびスプール８９の軸方向位置は、上記磁力とスプリング９１による付勢力とのバランスにより決まる。電磁駆動部ＭＤは、コイル１２が通電されると、プランジャ１１を軸方向へ移動させる磁力を発生可能である。
</base:Paragraphs>
      <base:Paragraphs num="0026">
  （特徴構成）
  次に、電磁アクチュエータ１０の特徴構成を図４、図５に基づき説明する。図４、図５では、特徴構成を分かり易くするために各部は模式的に示されており、各部の寸法、角度および寸法比は必ずしも正確なものではない。
</base:Paragraphs>
      <base:Paragraphs num="0027">
  以下の説明において、通孔３３の縁のうち、軸方向の一方側に位置する縁を第１縁４０とする。また、通孔３３のうち、軸方向の他方側に位置する縁を第２縁４１とする。
  また、図４に示すようにロッド１７が最大引込位置に位置するとき、ロッド１７のうち、軸方向位置が第１縁４０と一致する箇所を第１先端側特定箇所Ｐｓ１とし、また、ロッド１７のうち、軸方向位置が第２縁４１と一致する箇所を第２先端側特定箇所Ｐｓ２とする。第１先端側特定箇所Ｐｓ１および第２先端側特定箇所Ｐｓ２は、二点鎖線を用いて仮想的に示されている。
</base:Paragraphs>
      <base:Paragraphs num="0028">
  また、図５に示すように、ロッド１７が最大突出位置に位置するとき、ロッド１７のうち、軸方向位置が第２縁４１と一致する箇所を第１基端側特定箇所Ｐｋ１とし、また、ロッド１７のうち、軸方向位置が第１縁４０と一致する箇所を第２基端側特定箇所Ｐｋ２とする。第１基端側特定箇所Ｐｋ１および第２基端側特定箇所Ｐｋ２は、二点鎖線を用いて仮想的に示されている。
</base:Paragraphs>
      <base:Paragraphs num="0029">
  ロッド１７は、軸方向へ移動するときに通孔３３の内壁面３４と摺動可能な外壁面４２を有する。外壁面４２は、少なくとも第１基端側特定箇所Ｐｋ１から第１先端側特定箇所Ｐｓ１までの軸方向範囲において、ロッド１７の基端４３側から先端４４側に向かって径が小さくなるテーパ状に形成されている。本実施形態では、外壁面４２は、基端４３から先端４４までの全範囲でテーパ状である。
</base:Paragraphs>
      <base:Paragraphs num="0030">
  「ロッド１７の外壁面４２と通孔３３の内壁面３４とのクリアランス」とは、ロッド１７と通孔３３とが互いに同心であるとき、外壁面４２から内壁面３４までの間隔の最小値のことである。ロッド１７が最大引込位置に位置するときのクリアランスをＣＡとし、ロッド１７が最大突出位置に位置するときのクリアランスをＣＢとする。
</base:Paragraphs>
      <base:Paragraphs num="0031">
  カバー１８は、板材からプレス加工により成形されている。通孔３３の内壁面３４は、第１縁４０側から第２縁４１側に向かって径が小さくなるテーパ状である。外壁面４２の勾配は、通孔３３の内壁面３４の勾配よりも大きい。これにより、ロッド１７の外壁面４２から通孔３３の内壁面３４までのクリアランスは、ロッド１７の軸方向位置にかかわらず、軸方向の一方側ほど小さくなっている。外壁面４２の勾配とは、外壁面４２と軸心ＡＸとのなす角度のことである。通孔３３の内壁面３４の勾配とは、通孔３３の内壁面３４と軸心ＡＸとのなす角度のことである。
  図４、図５では、外壁面４２の勾配および通孔３３の内壁面３４の勾配を実際よりも大きく示している。また、クリアランスを実際よりも大きく示している。
</base:Paragraphs>
      <base:Paragraphs num="0032">
  以上のように、第１縁４０と第２縁４１との間の軸方向範囲において、ロッド１７が最大突出位置に位置するときのクリアランスＣＢは、最大引込位置に位置するときのクリアランスＣＡよりも小さい、すなわち、ＣＡ＞ＣＢの関係が成り立っている。
</base:Paragraphs>
      <base:Paragraphs num="0033">
  （比較形態）
  ここで、２つの比較形態を示すことで、本実施形態の有利な点を明らかにする。
  図１９に模式的に示すように、第１比較形態では、ロッド１００の外壁面１０１が軸心ＡＸと平行な円筒面であるとともに、通孔１０２の内壁面が軸心ＡＸと平行な円筒面である。ロッド１００の外壁面１０１と通孔１０２の内壁面とのクリアランスをＣ１とする。クリアランスＣ１は、ロッド１００の軸方向位置にかかわらず、本実施形態においてロッド１７が最大突出位置に位置するときのクリアランスＣＡと同等となるように、比較的小さく設定されている。
</base:Paragraphs>
      <base:Paragraphs num="0034">
  このような第１比較形態によると、図２０に示すように、ロッド１００のストローク量の全域においてロッド１００の径方向振れ量を比較的小さく抑えることができる。しかし、外壁面１０１と通孔１０２の内壁面との摩擦力が比較的大きくなってしまう。これにより、ロッド１００および支持筒部１０３の摩耗が増えるとともに、ロッド１００が移動不能となる所謂こじりが発生するおそれがある。
</base:Paragraphs>
      <base:Paragraphs num="0035">
  図２１に模式的に示すように、第２比較形態では、ロッド１０５の外壁面１０６が軸心ＡＸと平行な円筒面であるとともに、通孔１０２の内壁面が軸心ＡＸと平行な円筒面である。ロッド１０５の外壁面１０６と通孔１０２の内壁面とのクリアランスをＣ２とする。クリアランスＣ２は、ロッド１０５の軸方向位置にかかわらず、本実施形態においてロッド１７が最大引込位置に位置するときのクリアランスＣＢと同等となるように、比較的大きく設定されている。
</base:Paragraphs>
      <base:Paragraphs num="0036">
  このような第２比較形態によると、図２２に示すように、ロッド１０５のストローク量の全域において外壁面１０６と通孔１０２の内壁面との摩擦力を比較的小さく抑えることができる。しかし、ロッド１０５の径方向振れ量が比較的大きくなってしまう。特に、ロッド１０５のストローク量が大きいとき、磁力増大の影響でプランジャに対する径方向の力（サイドフォース）が大きくなり、ロッド１０５が径方向へ大きく振れてしまう。
</base:Paragraphs>
      <base:Paragraphs num="0037">
  一方、第１実施形態では、ロッド１７が最大突出位置に位置するときのクリアランスＣＡは第１比較形態におけるクリアランスＣ１と同等であるとともに、ロッド１７が最大引込位置に位置するときのクリアランスＣＢは第２比較形態におけるクリアランスＣ２と同等である。そのため、図６に示すように、ロッド１７のストローク量の全域において、ロッド１７の径方向振れ量を比較的小さく抑えつつ、外壁面４２と通孔３３の内壁面３４との摩擦力を比較的小さく抑えることができる。
</base:Paragraphs>
      <base:Paragraphs num="0038">
  （効果）
  以上説明したように、第１実施形態では、ロッド１７は、少なくとも第１基端側特定箇所Ｐｋ１から第１先端側特定箇所Ｐｓ１までの軸方向範囲において、ロッド１７の基端４３側から先端４４側に向かって径が小さくなるテーパ状の外壁面４２を有する。これにより、ロッド１７が最大突出位置に位置するときのクリアランスＣＢは、ロッド１７が最大引込位置に位置するときのクリアランスＣＡよりも小さい。
</base:Paragraphs>
      <base:Paragraphs num="0039">
  このように構成すれば、ロッド１７が引き込み側に位置するときのロッド１７と通孔３３の内壁面３４とのクリアランス（引込時クリアランス）を比較的大きくしつつ、ロッド１７が突き出し側に位置するときのロッド１７と通孔３３の内壁面３４とのクリアランス（突出時クリアランス）を比較的小さくすることができる。したがって、引込時クリアランスが比較的大きいことによって、ロッド１７と支持筒部３２との摩擦力を低減可能である。また、突出時クリアランスが比較的小さいことによって、ロッド１７の先端４４の径方向への振れ量を低減可能である。つまり、ロッド１７と支持筒部３２との摩擦力低減と、ロッド１７の先端４４の径方向への振れ量低減との両立を図ることができる。
</base:Paragraphs>
      <base:Paragraphs num="0040">
  また、第１実施形態では、外壁面４２は、少なくとも第１基端側特定箇所Ｐｋ１から第２先端側特定箇所Ｐｓ２までの軸方向範囲においてテーパ状である。
  このように構成すれば、ロッド１７のうち、第１先端側特定箇所Ｐｓ１から先端４４側の外周面が軸方向と平行である場合と比べて、引込時クリアランスが大きくなる。したがって、ロッド１７と支持筒部３２との摩擦力を一層低減可能である。
</base:Paragraphs>
      <base:Paragraphs num="0041">
  また、第１実施形態では、外壁面４２は、少なくとも第２基端側特定箇所Ｐｋ２から第１先端側特定箇所Ｐｓ１までの軸方向範囲においてテーパ状である。
  このように構成すれば、ロッド１７のうち、第１基端側特定箇所Ｐｋ１から基端４３側の外周面が軸方向と平行である場合と比べて、突出時クリアランスが小さくなる。したがって、ロッド１７の先端４４の径方向への振れ量を一層低減可能である。
</base:Paragraphs>
      <base:Paragraphs num="0042">
  また、第１実施形態では、通孔３３の内壁面３４は、第１縁４０側から第２縁４１側に向かって径が小さくなるテーパ状である。外壁面４２の勾配は、通孔３３の内壁面３４の勾配よりも大きい。
  このように構成すれば、外壁面４２と通孔３３の内壁面３４とのクリアランスは、ロッド１７の軸方向位置にかかわらず、軸方向の一方側ほど狭くなる。したがって、図７に示すように、ロッド１７が径方向へ振れたときに外壁面４２と通孔３３の内壁面３４とが面接触するように構成することができる。
</base:Paragraphs>
      <base:Paragraphs num="0043">
  ［第２実施形態］
  本発明の第２実施形態では、図８に示すように、外壁面５０は、第１基端側特定箇所Ｐｋ１から第１先端側特定箇所Ｐｓ１までの軸方向範囲においてテーパ状である。外壁面５０は、第１先端側特定箇所Ｐｓ１から先端４４側が軸方向と平行であるとともに、第１基端側特定箇所Ｐｋ１から基端４３側が軸方向と平行である。このように外壁面５０の一部がテーパ状であっても、第１、第２比較形態と比べると、ロッド１７と支持筒部３２との摩擦力低減とロッド１７の先端４４の径方向への振れ量低減との両立を図ることができる。
</base:Paragraphs>
      <base:Paragraphs num="0044">
  ［第３実施形態］
  本発明の第３実施形態では、図９に示すように、基端４３側から先端４４側に向かって、所定の間隔で段階的にロッド１７の径が小さくなるように、外壁面６０が段付き形状に形成されている。ロッド１７の径が小さくなる間隔は、任意に設定してもよい。本実施形態では、外壁面６０は、基端４３側から先端４４側までの全範囲に対して階段状である。このような階段状のロッドにおいても、ロッド１７が最大引込位置に位置するときのクリアランスＣＡよりも、ロッド１７が最大突出位置に位置するときのクリアランスＣＢよりも小さくなる。したがって、第１実施形態と同様の効果を奏する。
</base:Paragraphs>
      <base:Paragraphs num="0045">
  ［第４実施形態］
  本発明の第４実施形態では、図１０に示すように、第１基端側特定箇所Ｐｋ１から第２基端側特定箇所Ｐｋ２までの軸方向範囲において、ロッド１７が突起７１を有する。ロッド１７が突起７１を有することで、外壁面７０は突出面７２を含む。外壁面７０が突出面７２を含むことにより、ロッド１７が最大引込位置に位置するときのクリアランスＣＡよりも、ロッド１７が最大突出位置に位置するときのクリアランスＣＢよりも小さくなる。したがって、第４実施形態においても、第１実施形態と同様の効果を奏する。
</base:Paragraphs>
      <base:Paragraphs num="0046">
  ［他の実施形態］
  第２実施形態の思想を共有する他の実施形態では、図１１に示すように、第２基端側特定箇所Ｐｋ２から第１基端側特定箇所Ｐｋ１までの軸方向範囲において、外壁面５１を基端４３側から先端４４側に向かって径が小さくなるテーパ状としてもよい。
  図１２に示すように、第１先端側特定箇所Ｐｓ１から第２先端側特定箇所Ｐｓ２までの軸方向範囲において、外壁面５２を基端４３側から先端４４側に向かって径が小さくなるテーパ状としてもよい。
</base:Paragraphs>
      <base:Paragraphs num="0047">
  図１３に示すように、第２基端側特定箇所Ｐｋ２から第１先端側特定箇所Ｐｓ１までの軸方向範囲において、外壁面５３を基端４３側から先端４４側に向かって径が小さくなるテーパ状としてもよい。
  図１４に示すように、第１基端側特定箇所Ｐｋ１から第２先端側特定箇所Ｐｓ２までの軸方向範囲において、外壁面５４を基端４３側から先端４４側に向かって径が小さくなるテーパ状としてもよい。
  図１５に示すように、第２基端側特定箇所Ｐｋ２から第２先端側特定箇所Ｐｓ２までの軸方向範囲において、外壁面５５を基端４３側から先端４４側に向かって径が小さくなるテーパ状としてもよい。
</base:Paragraphs>
      <base:Paragraphs num="0048">
  図１６に示すように、第１先端側特定箇所Ｐｓ１と第２先端側特定箇所Ｐｓ２との間Ｐｓ２１から第１基端側特定箇所Ｐｋ１と第２基端側特定箇所Ｐｋ２との間Ｐｋ１２までの軸方向範囲において、外壁面５６を基端４３側から先端４４側に向かって径が小さくなるテーパ状としてもよい。
</base:Paragraphs>
      <base:Paragraphs num="0049">
  また、第１先端側特定箇所と第２先端側特定箇所との間から第１基端側特定箇所と第１先端端側特定箇所との間までの軸方向範囲において、外壁面を基端側から先端側に向かって径が小さくなるテーパ状としてもよい。さらに第１基端側特定箇所と第１先端端側特定箇所との間から第１基端側特定箇所と第２基端側特定箇所との間までの軸方向範囲において、外壁面を基端側から先端側に向かって径が小さくなるテーパ状としてもよい。
</base:Paragraphs>
      <base:Paragraphs num="0050">
  第３実施形態の思想を共有する他の実施形態では、図１７に示すように、第１先端側特定箇所Ｐｓ１から第２基端側特定箇所Ｐｋ２までの軸方向範囲の一部において、ロッド１７の外壁面６１を段になっている段付き形状としてもよい。第１実施形態と同様の効果を奏する。
</base:Paragraphs>
      <base:Paragraphs num="0051">
  第４実施形態の思想を共有する他の実施形態では、ロッドは、軸および軸に嵌合するリングを有し、突起はリングから構成されてもよい。
</base:Paragraphs>
      <base:Paragraphs num="0052">
  本発明の他の実施形態では、カバーを複数のカバー体に分割し、可動部とは別の駆動部を用いて、複数のカバー体を径方向内側に動作可能にする。ロッドが最大引込位置から最大突出位置に摺動するとき、カバーをロッドに接近させる。ロッドが摺動するときにカバーを接近させることで、ロッドが最大突出位置に位置するときのクリアランスを、ロッド最大引込位置に位置するときのクリアランスよりも小さくすることができる。
</base:Paragraphs>
      <base:Paragraphs num="0053">
  本発明の他の実施形態では、ロッドは、プランジャと同一部材から構成されてもよい。
  本発明の他の実施形態では、カバーは、プレス加工による成形品に限らず、例えば切削加工による成形品であってもよい。
  本発明の他の実施形態では、カバーの通孔の内壁面は、軸方向と平行な円筒面であってもよい。
</base:Paragraphs>
      <base:Paragraphs num="0054">
  本発明の他の実施形態では、カバーは、ヨークと同一部材から構成されてもよい。
  本発明の他の実施形態では、カバーの第１縁４０側の角部４０１は、丸みを帯びている形状に限らず、例えばＣ面取り形状であってもよいし、図１８に示すように尖鋭形状であってもよい。
  本発明は、上述した実施形態に限定されるものではなく、発明の趣旨を逸脱しない範囲で種々の形態で実施可能である。
</base:Paragraphs>
    </business:EmbodimentsDescription>
    <business:ReferenceSignsList>
      <base:Paragraphs num="0055">
  １１・・・可動部                      １２・・・コイル
  １７・・・出力軸部                    １８・・・支持部
  ３３・・・通孔                        ３４・・・内壁面
  ４０・・・第１縁                      ４１・・・第２縁
  ４２、５０、６０、７０・・・外壁面
  ４３・・・基端                        ４４・・・先端
  ＭＤ・・・電磁駆動部
</base:Paragraphs>
    </business:ReferenceSignsList>
  </business:Description>
  <business:Drawings lang="ja" sourceDB="JP">
    <base:Figure num="0001">
      <base:Image id="000003" he="122" wi="83" file="2016127266_000003.TIF" imgContent="drawing" imgFormat="TIFF" />
    </base:Figure>
    <base:Figure num="0002">
      <base:Image id="000004" he="122" wi="83" file="2016127266_000004.TIF" imgContent="drawing" imgFormat="TIFF" />
    </base:Figure>
    <base:Figure num="0003">
      <base:Image id="000005" he="122" wi="83" file="2016127266_000005.TIF" imgContent="drawing" imgFormat="TIFF" />
    </base:Figure>
    <base:Figure num="0004">
      <base:Image id="000006" he="122" wi="83" file="2016127266_000006.TIF" imgContent="drawing" imgFormat="TIFF" />
    </base:Figure>
    <base:Figure num="0005">
      <base:Image id="000007" he="122" wi="83" file="2016127266_000007.TIF" imgContent="drawing" imgFormat="TIFF" />
    </base:Figure>
    <base:Figure num="0006">
      <base:Image id="000008" he="122" wi="83" file="2016127266_000008.TIF" imgContent="drawing" imgFormat="TIFF" />
    </base:Figure>
    <base:Figure num="0007">
      <base:Image id="000009" he="122" wi="83" file="2016127266_000009.TIF" imgContent="drawing" imgFormat="TIFF" />
    </base:Figure>
    <base:Figure num="0008">
      <base:Image id="000010" he="122" wi="83" file="2016127266_000010.TIF" imgContent="drawing" imgFormat="TIFF" />
    </base:Figure>
    <base:Figure num="0009">
      <base:Image id="000011" he="122" wi="83" file="2016127266_000011.TIF" imgContent="drawing" imgFormat="TIFF" />
    </base:Figure>
    <base:Figure num="0010">
      <base:Image id="000012" he="122" wi="83" file="2016127266_000012.TIF" imgContent="drawing" imgFormat="TIFF" />
    </base:Figure>
    <base:Figure num="0011">
      <base:Image id="000013" he="122" wi="83" file="2016127266_000013.TIF" imgContent="drawing" imgFormat="TIFF" />
    </base:Figure>
    <base:Figure num="0012">
      <base:Image id="000014" he="122" wi="83" file="2016127266_000014.TIF" imgContent="drawing" imgFormat="TIFF" />
    </base:Figure>
    <base:Figure num="0013">
      <base:Image id="000015" he="122" wi="83" file="2016127266_000015.TIF" imgContent="drawing" imgFormat="TIFF" />
    </base:Figure>
    <base:Figure num="0014">
      <base:Image id="000016" he="122" wi="83" file="2016127266_000016.TIF" imgContent="drawing" imgFormat="TIFF" />
    </base:Figure>
    <base:Figure num="0015">
      <base:Image id="000017" he="122" wi="83" file="2016127266_000017.TIF" imgContent="drawing" imgFormat="TIFF" />
    </base:Figure>
    <base:Figure num="0016">
      <base:Image id="000018" he="122" wi="83" file="2016127266_000018.TIF" imgContent="drawing" imgFormat="TIFF" />
    </base:Figure>
    <base:Figure num="0017">
      <base:Image id="000019" he="122" wi="83" file="2016127266_000019.TIF" imgContent="drawing" imgFormat="TIFF" />
    </base:Figure>
    <base:Figure num="0018">
      <base:Image id="000020" he="122" wi="83" file="2016127266_000020.TIF" imgContent="drawing" imgFormat="TIFF" />
    </base:Figure>
    <base:Figure num="0019">
      <base:Image id="000021" he="122" wi="83" file="2016127266_000021.TIF" imgContent="drawing" imgFormat="TIFF" />
    </base:Figure>
    <base:Figure num="0020">
      <base:Image id="000022" he="122" wi="83" file="2016127266_000022.TIF" imgContent="drawing" imgFormat="TIFF" />
    </base:Figure>
    <base:Figure num="0021">
      <base:Image id="000023" he="122" wi="83" file="2016127266_000023.TIF" imgContent="drawing" imgFormat="TIFF" />
    </base:Figure>
    <base:Figure num="0022">
      <base:Image id="000024" he="122" wi="83" file="2016127266_000024.TIF" imgContent="drawing" imgFormat="TIFF" />
    </base:Figure>
  </business:Drawings>
  <business:Claims lang="ja" dataFormat="original" sourceDB="JP">
    <business:Claim num="0001">
      <business:ClaimText>
  所定の直線方向へ往復移動可能な可動部（１１）と、
  環状のコイル（１２）を有し、前記コイルが通電されると、前記可動部を前記直線方向へ移動させる磁力を発生可能な電磁駆動部（ＭＤ）と、
  前記可動部から前記直線方向へ突き出すように設けられ、前記直線方向の一方側に位置する最大引込位置から前記直線方向の他方側に位置する最大突出位置まで前記可動部と共に移動可能なロッド（１７）と、
  を備え、
  前記電磁駆動部は、前記ロッドが挿通している通孔（３３）を有し、
  前記ロッドは、前記通孔と摺動可能な外壁面（４２、５０、６０、７０）を有し、
  前記最大突出位置に位置する前記ロッドの前記外壁面から前記通孔の内壁面（３４）までのクリアランス（ＣＢ）は、前記最大引込位置に位置する前記ロッドの前記外壁面から前記内壁面までのクリアランス（ＣＡ）よりも小さい電磁アクチュエータ。
</business:ClaimText>
    </business:Claim>
    <business:Claim num="0002">
      <business:ClaimText>
  前記通孔のうち、前記直線方向の一方側に位置する縁を第１縁（４０）とし、
  前記通孔のうち、前記直線方向の他方側に位置する縁を第２縁（４１）とし、
  前記ロッドが前記最大引込位置に位置するとき、前記ロッドのうち、軸方向位置が前記第１縁と一致する箇所を第１先端側特定箇所（Ｐｓ１）とし、
  前記ロッドが前記最大引込位置に位置するとき、前記ロッドのうち、軸方向位置が前記第２縁と一致する箇所を第２先端側特定箇所（Ｐｓ２）とし、
  前記ロッドが前記最大突出位置に位置するとき、前記ロッドのうち、軸方向位置が前記第２縁と一致する箇所を第１基端側特定箇所（Ｐｋ１）とし、
  前記ロッドが前記最大突出位置に位置するとき、前記ロッドのうち、軸方向位置が前記第１縁と一致する箇所を第２基端側特定箇所（Ｐｋ２）とすると、
  前記外壁面は、少なくとも前記第１基端側特定箇所（Ｐｋ１）から前記第１先端側特定箇所（Ｐｓ１）までの軸方向範囲において、前記ロッドの基端（４３）側から先端（４４）側に向かって径が小さくなるテーパ状である請求項１に記載の電磁アクチュエータ。
</business:ClaimText>
    </business:Claim>
    <business:Claim num="0003">
      <business:ClaimText>
  前記外壁面は、少なくとも前記第２基端側特定箇所（Ｐｋ２）から前記第１基端側特定箇所（Ｐｋ１）までの軸方向範囲において、前記基端側から前記先端側に向かって径が小さくなるテーパ状である請求項２に記載の電磁アクチュエータ。
</business:ClaimText>
    </business:Claim>
    <business:Claim num="0004">
      <business:ClaimText>
  前記外壁面は、少なくとも前記第１先端側特定箇所（Ｐｓ１）から前記第２先端側特定箇所（Ｐｓ２）までの軸方向範囲において、前記基端側から前記先端側に向かって径が小さくなるテーパ状である請求項２または３に記載の電磁アクチュエータ。
</business:ClaimText>
    </business:Claim>
    <business:Claim num="0005">
      <business:ClaimText>
  前記外壁面は、前記ロッドの基端から先端に向かって径が小さくなるテーパ状である請求項１に記載の電磁アクチュエータ。
</business:ClaimText>
    </business:Claim>
    <business:Claim num="0006">
      <business:ClaimText>
  前記外壁面は、前記ロッドの基端から先端に向かって、径が段階的に小さくなる段付き形状である請求項１に記載の電磁アクチュエータ。
</business:ClaimText>
    </business:Claim>
    <business:Claim num="0007">
      <business:ClaimText>
  前記ロッドが前記最大突出位置に位置するとき、前記ロッドのうち、軸方向位置が前記第２縁と一致する箇所を第１基端側特定箇所（Ｐｋ１）とし、
  前記ロッドが前記最大突出位置に位置するとき、前記ロッドのうち、軸方向位置が前記第１縁と一致する箇所を第２基端側特定箇所（Ｐｋ２）とすると、
  前記外壁面は、第２基端側特定箇所（Ｐｋ２）から第１基端側特定箇所（Ｐｋ１）までの軸方向範囲において、少なくとも１つの突出面（７２）を含む請求項１に記載の電磁アクチュエータ。
</business:ClaimText>
    </business:Claim>
  </business:Claims>
</business:PatentDocumentAndRelated>