<?xml version="1.0" encoding="UTF-8"?><!DOCTYPE PatentDocumentAndRelated  SYSTEM '/DTDS/ExternalStandards/ipphdb-entities.dtd' []><business:PatentDocumentAndRelated xmlns:base="http://www.sipo.gov.cn/XMLSchema/base" xmlns:business="http://www.sipo.gov.cn/XMLSchema/business" xmlns:m="http://www.w3.org/1998/Math/MathML" xmlns:tbl="http://oasis-open.org/specs/soextblx" xmlns:xsi="http://www.w3.org/2001/XMLSchema-instance" xsi:schemaLocation="http://www.sipo.gov.cn/XMLSchema/business /DTDS/PatentDocument/Elements/OtherElements.xsd" xsdVersion="V2.2.1" file="JP102015000200883JP00020161247820AFULJA20160711JP00K.XML" dateProduced="20160812" status="C" lang="ja" country="JP" docNumber="2016124782" kind="A" datePublication="20160711">
  <business:BibliographicData lang="ja" country="JP">
    <business:PublicationReference dataFormat="standard" sequence="1">
      <base:DocumentID>
        <base:WIPOST3Code>JP</base:WIPOST3Code>
        <base:DocNumber>2016124782</base:DocNumber>
        <base:Kind>A</base:Kind>
        <base:Date>20160711</base:Date>
      </base:DocumentID>
    </business:PublicationReference>
    <business:PublicationReference dataFormat="original" sourceDB="JP" sequence="1">
      <base:DocumentID>
        <base:WIPOST3Code>JP</base:WIPOST3Code>
        <base:DocNumber>2016124782</base:DocNumber>
        <base:Kind>A</base:Kind>
        <base:Date>20160711</base:Date>
      </base:DocumentID>
    </business:PublicationReference>
    <business:PlainLanguageDesignation lang="ja">公開特許公報(A)</business:PlainLanguageDesignation>
    <business:PublicAvailabilityDate>
      <business:PrintedWithGrant kind="patent">
        <base:DocumentID>
          <base:DocNumber>5856348</base:DocNumber>
          <base:Date>20160209</base:Date>
        </base:DocumentID>
      </business:PrintedWithGrant>
    </business:PublicAvailabilityDate>
    <business:ApplicationReference applType="10" dataFormat="standard" sequence="1">
      <base:DocumentID>
        <base:WIPOST3Code>JP</base:WIPOST3Code>
        <base:DocNumber>102015000200883</base:DocNumber>
        <base:Date>20151009</base:Date>
      </base:DocumentID>
    </business:ApplicationReference>
    <business:ApplicationReference applType="10" dataFormat="original" sequence="1" sourceDB="JP">
      <base:DocumentID>
        <base:WIPOST3Code>JP</base:WIPOST3Code>
        <base:DocNumber>2015200883</base:DocNumber>
        <base:Date>20151009</base:Date>
      </base:DocumentID>
    </business:ApplicationReference>
    <business:PriorityDetails>
      <business:Priority kind="national" dataFormat="standard" sequence="1">
        <base:WIPOST3Code>JP</base:WIPOST3Code>
        <base:DocNumber>002014000264443</base:DocNumber>
        <base:Date>20141226</base:Date>
      </business:Priority>
      <business:Priority kind="national" dataFormat="original" sourceDB="JP" sequence="1">
        <base:WIPOST3Code>JP</base:WIPOST3Code>
        <base:DocNumber>2014264443</base:DocNumber>
        <base:Date>20141226</base:Date>
      </business:Priority>
    </business:PriorityDetails>
    <business:ClassificationIPCRDetails>
      <business:ClassificationIPCR sequence="1">
        <business:IPCVersionDate>20060101</business:IPCVersionDate>
        <business:ClassificationLevel>A</business:ClassificationLevel>
        <business:Section>C</business:Section>
        <business:MainClass>04</business:MainClass>
        <business:Subclass>B</business:Subclass>
        <business:MainGroup>35</business:MainGroup>
        <business:Subgroup>50</business:Subgroup>
        <business:SymbolPosition>F</business:SymbolPosition>
        <business:ClassificationValue>I</business:ClassificationValue>
        <base:ActionDate>
          <base:Date>20160613</base:Date>
        </base:ActionDate>
        <business:GeneratingOffice>
          <base:WIPOST3Code>JP</base:WIPOST3Code>
        </business:GeneratingOffice>
        <business:ClassificationStatus>B</business:ClassificationStatus>
        <business:ClassificationDataSource>H</business:ClassificationDataSource>
        <base:Text>C04B  35/50        20060101AFI20160613BHJP        </base:Text>
      </business:ClassificationIPCR>
      <business:ClassificationIPCR sequence="2">
        <business:IPCVersionDate>20160101</business:IPCVersionDate>
        <business:ClassificationLevel>A</business:ClassificationLevel>
        <business:Section>H</business:Section>
        <business:MainClass>01</business:MainClass>
        <business:Subclass>M</business:Subclass>
        <business:MainGroup>8</business:MainGroup>
        <business:Subgroup>0202</business:Subgroup>
        <business:SymbolPosition>L</business:SymbolPosition>
        <business:ClassificationValue>N</business:ClassificationValue>
        <base:ActionDate>
          <base:Date>20160613</base:Date>
        </base:ActionDate>
        <business:GeneratingOffice>
          <base:WIPOST3Code>JP</base:WIPOST3Code>
        </business:GeneratingOffice>
        <business:ClassificationStatus>B</business:ClassificationStatus>
        <business:ClassificationDataSource>H</business:ClassificationDataSource>
        <base:Text>H01M   8/0202      20160101ALN20160613BHJP        </base:Text>
      </business:ClassificationIPCR>
      <business:ClassificationIPCR sequence="3">
        <business:IPCVersionDate>20160101</business:IPCVersionDate>
        <business:ClassificationLevel>A</business:ClassificationLevel>
        <business:Section>H</business:Section>
        <business:MainClass>01</business:MainClass>
        <business:Subclass>M</business:Subclass>
        <business:MainGroup>8</business:MainGroup>
        <business:Subgroup>12</business:Subgroup>
        <business:SymbolPosition>L</business:SymbolPosition>
        <business:ClassificationValue>N</business:ClassificationValue>
        <base:ActionDate>
          <base:Date>20160613</base:Date>
        </base:ActionDate>
        <business:GeneratingOffice>
          <base:WIPOST3Code>JP</base:WIPOST3Code>
        </business:GeneratingOffice>
        <business:ClassificationStatus>B</business:ClassificationStatus>
        <business:ClassificationDataSource>H</business:ClassificationDataSource>
        <base:Text>H01M   8/12        20160101ALN20160613BHJP        </base:Text>
      </business:ClassificationIPCR>
    </business:ClassificationIPCRDetails>
    <business:JPClassification>
      <business:FI type="main">C04B35/50</business:FI>
      <business:FI type="additional">H01M8/02 Y</business:FI>
      <business:FI type="additional">H01M8/12</business:FI>
      <business:FClass>
        <business:FTerm>5H026AA06</business:FTerm>
      </business:FClass>
      <business:FClass>
        <business:FTerm>5H026CV02</business:FTerm>
      </business:FClass>
      <business:FClass>
        <business:FTerm>5H026CV05</business:FTerm>
      </business:FClass>
      <business:FClass>
        <business:FTerm>5H026EE13</business:FTerm>
      </business:FClass>
      <business:FClass>
        <business:FTerm>5H026HH03</business:FTerm>
      </business:FClass>
      <business:FClass>
        <business:FTerm>5H026HH05</business:FTerm>
      </business:FClass>
      <business:FClass>
        <business:Theme>5H026</business:Theme>
      </business:FClass>
    </business:JPClassification>
    <business:InventionTitle lang="ja" dataFormat="original" sourceDB="JP">互连器材料</business:InventionTitle>
    <business:Parties>
      <business:ApplicantDetails>
        <business:Applicant sequence="1" dataFormat="original" sourceDB="JP">
          <base:AddressBook lang="ja">
            <base:Name>日本碍子株式会社</base:Name>
            <base:RegisteredNumber>000004064</base:RegisteredNumber>
            <base:Address>
              <base:AddressLine>0</base:AddressLine>
              <base:AddressMailCode>0</base:AddressMailCode>
              <base:PostBox>0</base:PostBox>
              <base:AddressRoom>0</base:AddressRoom>
              <base:AddressFloor>0</base:AddressFloor>
              <base:AddressBuilding>0</base:AddressBuilding>
              <base:Street>0</base:Street>
              <base:AddressCity>0</base:AddressCity>
              <base:County>0</base:County>
              <base:City>0</base:City>
              <base:Province>0</base:Province>
              <base:PostCode>0</base:PostCode>
              <base:WIPOST3Code>XP</base:WIPOST3Code>
              <base:Text>愛知県名古屋市瑞穂区須田町2番56号</base:Text>
            </base:Address>
          </base:AddressBook>
          <business:OrganizationCode createDate="00000000" creator="00">0000000000</business:OrganizationCode>
        </business:Applicant>
      </business:ApplicantDetails>
      <business:InventorDetails>
        <business:Inventor sequence="1" dataFormat="original" sourceDB="JP">
          <base:AddressBook lang="ja">
            <base:Name>古賀  功一</base:Name>
            <base:Address>
              <base:AddressLine>0</base:AddressLine>
              <base:AddressMailCode>0</base:AddressMailCode>
              <base:PostBox>0</base:PostBox>
              <base:AddressRoom>0</base:AddressRoom>
              <base:AddressFloor>0</base:AddressFloor>
              <base:AddressBuilding>0</base:AddressBuilding>
              <base:Street>0</base:Street>
              <base:AddressCity>0</base:AddressCity>
              <base:County>0</base:County>
              <base:City>0</base:City>
              <base:Province>0</base:Province>
              <base:PostCode>0</base:PostCode>
              <base:WIPOST3Code>XP</base:WIPOST3Code>
              <base:Text>愛知県名古屋市瑞穂区須田町2番56号  日本碍子株式会社内</base:Text>
            </base:Address>
          </base:AddressBook>
        </business:Inventor>
        <business:Inventor sequence="2" dataFormat="original" sourceDB="JP">
          <base:AddressBook lang="ja">
            <base:Name>清水  壮太</base:Name>
            <base:Address>
              <base:AddressLine>0</base:AddressLine>
              <base:AddressMailCode>0</base:AddressMailCode>
              <base:PostBox>0</base:PostBox>
              <base:AddressRoom>0</base:AddressRoom>
              <base:AddressFloor>0</base:AddressFloor>
              <base:AddressBuilding>0</base:AddressBuilding>
              <base:Street>0</base:Street>
              <base:AddressCity>0</base:AddressCity>
              <base:County>0</base:County>
              <base:City>0</base:City>
              <base:Province>0</base:Province>
              <base:PostCode>0</base:PostCode>
              <base:WIPOST3Code>XP</base:WIPOST3Code>
              <base:Text>愛知県名古屋市瑞穂区須田町2番56号  日本碍子株式会社内</base:Text>
            </base:Address>
          </base:AddressBook>
        </business:Inventor>
        <business:Inventor sequence="3" dataFormat="original" sourceDB="JP">
          <base:AddressBook lang="ja">
            <base:Name>大森  誠</base:Name>
            <base:Address>
              <base:AddressLine>0</base:AddressLine>
              <base:AddressMailCode>0</base:AddressMailCode>
              <base:PostBox>0</base:PostBox>
              <base:AddressRoom>0</base:AddressRoom>
              <base:AddressFloor>0</base:AddressFloor>
              <base:AddressBuilding>0</base:AddressBuilding>
              <base:Street>0</base:Street>
              <base:AddressCity>0</base:AddressCity>
              <base:County>0</base:County>
              <base:City>0</base:City>
              <base:Province>0</base:Province>
              <base:PostCode>0</base:PostCode>
              <base:WIPOST3Code>XP</base:WIPOST3Code>
              <base:Text>愛知県名古屋市瑞穂区須田町2番56号  日本碍子株式会社内</base:Text>
            </base:Address>
          </base:AddressBook>
        </business:Inventor>
        <business:Inventor sequence="4" dataFormat="original" sourceDB="JP">
          <base:AddressBook lang="ja">
            <base:Name>海川  和之</base:Name>
            <base:Address>
              <base:AddressLine>0</base:AddressLine>
              <base:AddressMailCode>0</base:AddressMailCode>
              <base:PostBox>0</base:PostBox>
              <base:AddressRoom>0</base:AddressRoom>
              <base:AddressFloor>0</base:AddressFloor>
              <base:AddressBuilding>0</base:AddressBuilding>
              <base:Street>0</base:Street>
              <base:AddressCity>0</base:AddressCity>
              <base:County>0</base:County>
              <base:City>0</base:City>
              <base:Province>0</base:Province>
              <base:PostCode>0</base:PostCode>
              <base:WIPOST3Code>XP</base:WIPOST3Code>
              <base:Text>愛知県名古屋市瑞穂区須田町2番56号  日本碍子株式会社内</base:Text>
            </base:Address>
          </base:AddressBook>
        </business:Inventor>
        <business:Inventor sequence="5" dataFormat="original" sourceDB="JP">
          <base:AddressBook lang="ja">
            <base:Name>小原  隆平</base:Name>
            <base:Address>
              <base:AddressLine>0</base:AddressLine>
              <base:AddressMailCode>0</base:AddressMailCode>
              <base:PostBox>0</base:PostBox>
              <base:AddressRoom>0</base:AddressRoom>
              <base:AddressFloor>0</base:AddressFloor>
              <base:AddressBuilding>0</base:AddressBuilding>
              <base:Street>0</base:Street>
              <base:AddressCity>0</base:AddressCity>
              <base:County>0</base:County>
              <base:City>0</base:City>
              <base:Province>0</base:Province>
              <base:PostCode>0</base:PostCode>
              <base:WIPOST3Code>XP</base:WIPOST3Code>
              <base:Text>愛知県名古屋市瑞穂区須田町2番56号  日本碍子株式会社内</base:Text>
            </base:Address>
          </base:AddressBook>
        </business:Inventor>
      </business:InventorDetails>
      <business:AgentDetails>
        <business:CustomerNumber>00000</business:CustomerNumber>
        <business:Agent sequence="1" dataFormat="original" sourceDB="JP">
          <base:AddressBook lang="ja">
            <base:Name>新樹グローバル・アイピー特許業務法人</base:Name>
            <base:RegisteredNumber>110000202</base:RegisteredNumber>
          </base:AddressBook>
        </business:Agent>
      </business:AgentDetails>
    </business:Parties>
    <business:SpecificBibliographicData>
      <business:OriginalKindCode>A</business:OriginalKindCode>
    </business:SpecificBibliographicData>
    <business:StatisticalInformation>
      <business:ClaimsCount>2</business:ClaimsCount>
      <base:TotalPageCount>11</base:TotalPageCount>
    </business:StatisticalInformation>
  </business:BibliographicData>
  <business:Abstract dataFormat="original" lang="ja" sourceDB="JP">
    <base:Paragraphs>提供一种能够使互连器致密化的互连器材料。 互连器106材料,其含有碱土金属中的至少掺杂有钙的铬酸镧作为主成分,并且含有铬酸钙作为副成分,铬酸钙相对于至少掺杂有钙的铬酸镧的质量比为0.004以上,至少掺杂有钙的铬酸镧的晶格畸变为0.000007～0.008532 rad,铬酸钙的晶格畸变为0.000006～0.008080 rad。 图2</base:Paragraphs>
    <business:AbstractFigure>
      <base:Figure num="0001">
        <base:Image id="000002" he="62" wi="69" file="2016124782_000002.TIF" imgFormat="TIFF" imgContent="drawing"/>
      </base:Figure>
    </business:AbstractFigure>
  </business:Abstract>
  <business:Description dataFormat="original" sourceDB="JP">
    <business:TechnicalField>
      <base:Paragraphs num="0001">在此公开的技术涉及互连器材料。</base:Paragraphs>
    </business:TechnicalField>
    <business:BackgroundArt>
      <base:Paragraphs num="0002">以往,已知有在碱土类金属掺杂剂铬酸钙中添加有作为烧结辅助剂的铬酸钙的互连器材料（参照专利文献1）。 根据该互连器材料,碱土金属掺杂剂铬铁矿的烧结性提高,可以使燃料电池的互连器致密化。</base:Paragraphs>
      <base:Paragraphs num="0003">另一方面,已知仅通过增多铬酸钙的添加量,无法使互连器稳定地致密化（参照非专利文献1）。</base:Paragraphs>
    </business:BackgroundArt>
    <business:CitationList>
      <business:PatentDocumentation>
        <base:Paragraphs num="0004">           <business:ApplicationCitation num="0001">
            <base:Text>特開平5－170528号公報</base:Text>
          </business:ApplicationCitation> </base:Paragraphs>
      </business:PatentDocumentation>
      <business:NPL>
        <base:Paragraphs num="0005">           <business:NPLCitation num="0001">
            <base:Text>西山治男、相澤正信著「（La，Ca）CrO3のSOFCインタコネクターとしての特性（第1報）―焼結特性、電気伝導性―」Journal  of  the  Ceramic  Society  of  Japan  108［12］1103－1109（2000）」</base:Text>
          </business:NPLCitation> </base:Paragraphs>
      </business:NPL>
    </business:CitationList>
    <business:InventionSummary>
      <business:TechnicalProblem>
        <base:Paragraphs num="0006">本发明人等新发现,碱土金属中的铬酸钙相对于至少掺杂有钙的铬酸镧的质量比对烧结性造成影响。</base:Paragraphs>
        <base:Paragraphs num="0007">本发明是基于上述新见解而完成的,其课题在于提供一种能够使互连器致密化的互连器材料。</base:Paragraphs>
      </business:TechnicalProblem>
      <business:TechnicalSolution>
        <base:Paragraphs num="0008">本发明的互连器材料含有碱土金属中的至少掺杂有钙的铬酸镧作为主成分,并且含有铬酸钙作为副成分。 铬酸钙相对于至少掺杂有钙的铬酸镧的质量比为0.004以上。 至少掺杂有钙的铬酸镧的晶格畸变为0.000007 rad以上且0.008532 rad以下。 铬酸钙的晶格畸变为0.000006 rad以上且0.008080 rad以下。</base:Paragraphs>
      </business:TechnicalSolution>
      <business:AdvantageousEffects>
        <base:Paragraphs num="0009">根据本发明,可以提供能够使互连器致密化的互连器材料。</base:Paragraphs>
      </business:AdvantageousEffects>
    </business:InventionSummary>
    <business:DrawingsDescription>
      <base:Paragraphs num="0010">
        <base:FigureReference num="0001">图0001是表示燃料电池的结构的立体图。</base:FigureReference>
        <base:FigureReference num="0002">图0002是图1的I-I剖视图。</base:FigureReference>
      </base:Paragraphs>
    </business:DrawingsDescription>
    <business:EmbodimentsDescription>
      <base:Paragraphs num="0011">如后所述,互连器材料适合用作构成燃料电池的互连器的材料。 互连器材料含有碱土金属中的至少掺杂有钙的铬酸镧作为主成分,并且含有铬酸钙作为副成分。</base:Paragraphs>
      <base:Paragraphs num="0012">至少掺杂有钙的铬酸镧为La<base:Sub>1－w－x</base:Sub>Ca<base:Sub>w</base:Sub>Ma<base:Sub>x</base:Sub>Cr<base:Sub>1－y－z</base:Sub>Mb<base:Sub>y</base:Sub>O<base:Sub>3</base:Sub>（Ma为选自Sr和Ba中的至少1种碱土金属元素,Mb为选自Co、Ni、Mg和Al中的至少1种元素,0.025≤w≤0.3,0≤x≤0.3,0≤y≤0.22,-0.1≤z≤0.15）。 即,也可以在至少掺杂有钙的铬酸镧中掺杂有除钙以外的碱土金属元素。 作为至少掺杂有钙的铬酸镧的具体例,可列举出LCC（La）（La）；<base:Sub>0.7</base:Sub>Ca<base:Sub>0.3</base:Sub>CrO<base:Sub>3</base:Sub>）等。</base:Paragraphs>
      <base:Paragraphs num="0013">铬酸钙的组成由CaCrO<base:Sub>4</base:Sub>、CaCrO<base:Sub>4</base:Sub>·<base:Sub>2</base:Sub>H<base:Sub>2</base:Sub>O、CaCr<base:Sub>2</base:Sub>O<base:Sub>4</base:Sub>、Ca<base:Sub>3</base:Sub>（CrO<base:Sub>4</base:Sub>）2、Ca<base:Sub>5</base:Sub>（CrO<base:Sub>4</base:Sub>）<base:Sub>3</base:Sub>O或Ca<base:Sub>5</base:Sub>Cr<base:Sub>3</base:Sub>O<base:Sub>12</base:Sub>等表示。 这样的铬酸钙作为至少掺杂有钙的铬酸镧的烧结辅助剂发挥功能。 具体而言,铬酸钙在互连器材料的烧成时,至少抑制Cr<base:Sub>2</base:Sub>O<base:Sub>3</base:Sub>在掺杂有钙的铬酸镧的粒子间凝聚,并且促进粒子彼此的液相烧结。</base:Paragraphs>
      <base:Paragraphs num="0014">在此,铬酸钙相对于至少掺杂有钙的铬酸镧的质量比为0.004以上。 至少掺杂有钙的铬酸镧的含有率相对于互连器材料的总质量能够设为90wt%以上。 铬酸钙的含有率相对于互连器材料的总质量能够设为10wt%以下。 这样,在本实施方式中,主成分是指含有率为90wt%以上,副成分是指含有率为10wt%以下。</base:Paragraphs>
      <base:Paragraphs num="0015">至少掺杂有钙的铬酸镧的晶格畸变优选为0.000007 rad以上且0.008532 rad以下,更优选为0.000099 rad以上且0.004569 rad以下。 铬酸钙的晶格畸变优选为0.000006 rad～0.008080 rad,更优选为0.000094 rad～0.004987 rad。 另外,铬酸钙的a轴长可以设为以上以下。 铬酸钙的c轴长可以设为以上以下。 晶格畸变和晶格常数可以通过基于XRD的分析结果的Rietveld解析来求出。 具体而言,使用Bruker AXS公司制的D8ADVANCE装置,基于在衍射角2θ=10°～120°出现的至少掺杂有钙的铬酸镧和铬酸钙各自的峰位置,进行Rietveld分析,由此能够求出晶格畸变和晶格常数。</base:Paragraphs>
      <base:Paragraphs num="0016">2.对上述的互连器材料的制造方法进行说明。 在此,对使用LCC作为至少掺杂有钙的铬酸镧的一个例子的情况进行说明。</base:Paragraphs>
      <base:Paragraphs num="0017">首先,将La（NO：<base:Sub>3</base:Sub>）<base:Sub>3</base:Sub>·6H<base:Sub>2</base:Sub>O、Ca（NO；<base:Sub>3</base:Sub>）<base:Sub>3</base:Sub>·4H<base:Sub>2</base:Sub>O和Cr（NO；<base:Sub>3</base:Sub>）<base:Sub>3</base:Sub>·9H<base:Sub>2</base:Sub>准备O作为起始原料,将它们用上述组成式La表示。<base:Sub>1－w－x</base:Sub>Ca<base:Sub>w</base:Sub>Ma<base:Sub>x</base:Sub>Cr<base:Sub>1－y－z</base:Sub>Mb<base:Sub>y</base:Sub>O<base:Sub>3</base:Sub>（Ma为选自Sr和Ba中的至少1种碱土金属元素,Mb为选自Co、Ni、Mg和Al中的至少1种元素,0.025≤w≤0.3,0≤x≤0.3,0≤y≤0.22,-0.1≤z≤0.15）。</base:Paragraphs>
      <base:Paragraphs num="0018">接着,将称量的原料在水溶液中搅拌1小时～10小时后,将水溶液蒸发干固,得到液相合成粉末。</base:Paragraphs>
      <base:Paragraphs num="0019">接着,氧分压：10<base:Sup>－20</base:Sup>在atm～0.21 atm的气氛中,在800℃～1300℃的范围内将液相合成粉末预烧1～10小时,由此制造互连器材料。 此时,通过控制氧分压和预烧温度,使铬酸钙相对于LCC的质量比为0.004以上。 例如,若提高氧分压,则铬酸钙相对于LCC的质量比变大,若降低氧分压,则铬酸钙相对于LCC的质量比变小。 若提高预烧温度,则铬酸钙的质量比变小,若降低预烧温度,则铬酸钙的质量比变大。 铬酸钙相对于LCC的质量比可以通过基于XRD的分析结果的Rietveld解析来求出。 另外,通过控制氧分压和预烧温度,能够使LCC的晶格畸变为0.000007 rad～0.008532 rad,并且使铬酸钙的晶格畸变为0.000006 rad～0.008080 rad。 例如,若提高氧分压,则铬酸钙的含有率提高,LCC与铬酸钙的晶格畸变变小。 另一方面,若降低氧分压,则铬酸钙的含有率变低,LCC与铬酸钙的晶格畸变变大。 另外,若提高预烧温度,则铬酸钙的含有率变低,LCC与铬酸钙的晶格畸变变小。 另一方面,若降低预烧温度,则铬酸钙的含有率变高,LCC与铬酸钙的晶格畸变变大。</base:Paragraphs>
      <base:Paragraphs num="0020">需要说明的是,也可以通过在如上所述合成的单相的LCC中混合另外合成的单相的铬酸钙来制造互连器材料。 此时,以铬酸钙相对于LCC的质量比为0.004以上的方式进行称量。 铬酸钙相对于LCC的质量比可以由LCC与铬酸钙的称量比求出。</base:Paragraphs>
      <base:Paragraphs num="0021">3.作为具备互连器的燃料电池的一例,以横条纹型的固体氧化物型燃料电池（SOFC：Solid Oxide Fuel Cell）为例进行说明。 但是,燃料电池的形态不限于横条纹型,也可以是纵条纹型、燃料极支撑型、电解质平板型或圆筒型等。</base:Paragraphs>
      <base:Paragraphs num="0022">图1是表示燃料电池100的结构的立体图。 图2是图1的I-I剖视图。 燃料电池100包括支承基板101、燃料极102、电解质层103、阻挡层104、空气极105、互连器106以及集电部107。 燃料极102、电解质层103、阻挡层104以及空气极105构成单电池110的发电元件部。 互连器106将相邻的电池单元110电连接。</base:Paragraphs>
      <base:Paragraphs num="0023">支承基板101扁平且沿一个方向（z轴方向）延伸。 支撑基板101是具有电绝缘性的多孔质体。 支承基板101也可以包含镍。 支撑基板101可以含有Ni-Y<base:Sub>2</base:Sub>O<base:Sub>3</base:Sub>（镍-氧化钇）作为主成分。 镍可以以氧化物（NiO）的形式含有,发电时,NiO可以被氢气还原为Ni。</base:Paragraphs>
      <base:Paragraphs num="0024">在支承基板101的内部设置有流路101a。 流路101a沿着z轴方向延伸。 在发电时,在流路101a中流动的燃料气体通过支承基板101所具有的细孔向燃料极102供给。</base:Paragraphs>
      <base:Paragraphs num="0025">燃料极102设于支承基板101上。 燃料极102作为阳极发挥功能。 在支承基板101上,多个燃料极102隔开预定间隔地沿z轴方向排列。 作为燃料极102的材料,例如能够列举NiO-YSZ（氧化镍-氧化钇稳定化氧化锆）和/或NiO-Y<base:Sub>2</base:Sub>O<base:Sub>3</base:Sub>（氧化镍-氧化钇）。 燃料极102也可以具有燃料极集电层和燃料极活性层。 燃料极集电层配置于支承基板101上,燃料极活性层配置于燃料极集电层上。</base:Paragraphs>
      <base:Paragraphs num="0026">电解质层103设于燃料极102上。 电解质层103具有比支承基板101、燃料极102致密的构造。 相邻的2个电解质层103通过互连器106连接。 电解质层103和互连器106作为将空气和燃料气体分开的密封部发挥功能。 作为电解质层15的材料,例如可以举出8YSZ和10YSZ等氧化钇稳定化氧化锆、ScSZ（氧化钪稳定化氧化锆）等氧化锆系材料。</base:Paragraphs>
      <base:Paragraphs num="0027">阻隔层104设置于电解质层103与空气极105之间。 作为阻挡层104的材料,例如可举出GDC（（Ce,Gd）O<base:Sub>2</base:Sub>：钆掺杂氧化铈）、SDC（（Ce,Sm）O<base:Sub>2</base:Sub>：钐掺杂氧化铈）等。 阻隔层104具有抑制阳离子从空气极105向电解质层103扩散的功能。</base:Paragraphs>
      <base:Paragraphs num="0028">空气极105配置在阻隔层104上。 空气极50作为阴极发挥功能。 作为空气极105的材料,可列举出（La,Sr）（Co,Fe）O<base:Sub>3</base:Sub>、（La,Sr）FeO<base:Sub>3</base:Sub>、（La,Sr）CoO<base:Sub>3</base:Sub>、LaSrMnO<base:Sub>3</base:Sub>等钙钛矿型氧化物。</base:Paragraphs>
      <base:Paragraphs num="0029">互连器106配置在燃料极102上。 互连器106与相邻的2个电解质层103连接。 作为互连器106的材料,优选上述互连器材料。</base:Paragraphs>
      <base:Paragraphs num="0030">互连器106能够通过将使用了该互连器材料的成形体与燃料极102、电解质层103以及阻隔层104各自的成形体一起进行共烧（1300℃～1600℃、2小时～20小时）而形成。 此时,在上述的互连器材料中,如上所述,铬酸钙相对于至少掺杂有钙的铬酸镧的质量比被适当地调整,因此通过提高互连器106的烧结性,能够提高互连器106的致密度。 另外,在互连器材料所含有的铬酸镧和铬酸钙各自的晶格畸变被适当地调整的情况下,通过使互连器106和燃料极102的烧成收缩开始温度、烧成收缩量一致,能够抑制互连器106和燃料极102的界面剥离而提高两者的密合性。</base:Paragraphs>
      <base:Paragraphs num="0031">集电部107将互连器106与电池单元110电连接。 集电部107只要具有导电性即可,能够由与互连器106、空气极105同样的材料构成。</base:Paragraphs>
      <business:EmbodimentsExample>
        <base:Paragraphs num="0032">以下,对本发明的互连器材料的实施例进行说明。 但是,本发明并不限定于以下说明的实施例。</base:Paragraphs>
        <base:Paragraphs num="0033">[样品No.1～10的互连器材料的制作]如下制作样品No.1～10的互连器材料。</base:Paragraphs>
        <base:Paragraphs num="0034">首先,作为样品No.1～4、6～9的起始原料,准备La（NO<base:Sub>3</base:Sub>）<base:Sub>3</base:Sub>·6H<base:Sub>2</base:Sub>O、Ca（NO<base:Sub>3</base:Sub>）<base:Sub>3</base:Sub>·4H<base:Sub>2</base:Sub>O以及Cr（NO<base:Sub>3</base:Sub>）<base:Sub>3</base:Sub>·9H<base:Sub>2</base:Sub>O,作为样品No.5、10的起始原料,准备La（NO<base:Sub>3</base:Sub>）<base:Sub>3</base:Sub>·6H<base:Sub>2</base:Sub>O、Ca（NO<base:Sub>3</base:Sub>）<base:Sub>3</base:Sub>·4H<base:Sub>2</base:Sub>O、Cr（NO<base:Sub>3</base:Sub>）<base:Sub>3</base:Sub>·9H<base:Sub>2</base:Sub>O以及Sr（NO<base:Sub>3</base:Sub>）<base:Sub>2</base:Sub>·4H<base:Sub>2</base:Sub>O作为起始原料。 接着,将以满足上述组成式的方式称量的起始原料在水溶液中搅拌1～10小时后,将水溶液蒸发干固,得到液相合成粉末。</base:Paragraphs>
        <base:Paragraphs num="0035">接着,氧分压：10<base:Sup>－20</base:Sup>在atm～0.21 atm的气氛中,在800℃～1300℃的范围内将液相合成粉末预烧1～10小时,由此合成掺杂有钙的铬酸镧和铬酸钙。 此时,通过控制氧分压和预烧温度,如表1所示那样调整铬酸钙相对于掺杂有钙的铬酸镧的质量比。</base:Paragraphs>
        <base:Paragraphs num="0036">[样品No.1～10的互连器材料的相对密度测定]将样品No.1～10的互连器材料加压成型（1～5MPa）成棱柱状,进行烧成（1400℃、1～10小时）,由此制作试验片。 然后,通过图像解析法算出试验片的相对密度。 即,使用图像解析软件,由试验片的截面SEM照片算出气孔率。 将各样品的相对密度的计算结果汇总示于表1。</base:Paragraphs>
        <base:Paragraphs num="0037">
          <base:TableDetails num="0001">
            <base:Image id="000003" he="52" wi="151" file="2016124782_000003.TIF" imgContent="drawing" imgFormat="TIFF"/>
          </base:TableDetails>
        </base:Paragraphs>
        <base:Paragraphs num="0038">如表1所示,至少在铬酸钙相对于掺杂有钙的铬酸镧的质量比为0.004以上的样品中,能够得到能够充分用作互连器的95%以上的相对密度。</base:Paragraphs>
        <base:Paragraphs num="0039">这是因为,通过使互连器材料中的至少掺杂有钙的铬酸镧和铬酸钙的存在状态最佳化,能够促进互连器的液相烧结。</base:Paragraphs>
        <base:Paragraphs num="0040">[样品No.11～19的互连器材料的制作]如下制作样品No.11～19的互连器材料。</base:Paragraphs>
        <base:Paragraphs num="0041">首先,与上述的样品No.2～10的互连器材料同样地制作样品No.11～19的互连器材料。 此时,通过控制氧分压和预烧温度,至少如表2所示那样调整掺杂有钙的铬酸镧和铬酸钙的晶格畸变。</base:Paragraphs>
        <base:Paragraphs num="0042">晶格畸变通过基于XRD的分析结果的Rietveld解析而求出。</base:Paragraphs>
        <base:Paragraphs num="0043">[样品No.11～19的燃料极-互连器的制作]如以下那样制作了样品No.11～19的燃料极-互连器层叠体。</base:Paragraphs>
        <base:Paragraphs num="0044">首先,利用模具压制成型法对NiO-Y<base:Sub>2</base:Sub>O<base:Sub>3</base:Sub>粉末的混合粉末进行成型,形成燃料极的成型体。</base:Paragraphs>
        <base:Paragraphs num="0045">接着,在表2所示的互连器材料中混合水和粘合剂,将浆料涂布在燃料极的成型体上,形成互连器的成型体。</base:Paragraphs>
        <base:Paragraphs num="0046">接着,对燃料极的成型体和互连器的成型体进行共烧结（1400℃、1～10小时）。</base:Paragraphs>
        <base:Paragraphs num="0047">[样品No.11～19的烧成收缩起始温度、1300℃下的烧成收缩量的评价]将各样品的互连器材料压制成型（1～5MPa）成棱柱状,得到压制成型体。 接着,将压制成型体设置于Rigaku制的TP2热机械分析装置,在大气气氛中升温,评价由升温中的烧结引起的压制体的尺寸变化。 具体而言,将尺寸收缩0.5%时的温度作为烧成收缩开始温度。 另外,测定1300℃下的烧成收缩量。 将测定结果示于表2。</base:Paragraphs>
        <base:Paragraphs num="0048">[样品No.11～19所涉及的燃料极-互连器的剥离确认]使用电子显微镜来确认燃料极-互连器间有无剥离。 将确认结果示于表2。</base:Paragraphs>
        <base:Paragraphs num="0049">
          <base:TableDetails num="0002">
            <base:Image id="000004" he="212" wi="61" file="2016124782_000004.TIF" imgContent="drawing" imgFormat="TIFF"/>
          </base:TableDetails>
        </base:Paragraphs>
        <base:Paragraphs num="0050">如表2所示,在至少掺杂有钙的铬酸镧的晶格畸变为0.000007 rad以上且0.008532 rad以下、并且铬酸钙的晶格畸变为0.000006 rad以上且0.008080 rad以下的样品中,能够抑制互连器从燃料极剥离。</base:Paragraphs>
        <base:Paragraphs num="0051">这是因为互连器和燃料极的烧成收缩行为一致。</base:Paragraphs>
        <base:Paragraphs num="0052">另一方面,在样品No.11中,互连器比燃料极早开始烧结。 因此,互连器与燃料极的烧成收缩行为不一致而产生了剥离。 另外,在样品No.18、19中,互连器的烧成中途即1300℃下的烧成收缩量比燃料极大,因此互连器与燃料极的烧成收缩行为不一致而产生了剥离。</base:Paragraphs>
        <base:Paragraphs num="0053">另外,在至少掺杂有钙的铬酸镧的晶格畸变为0.000099 rad以上且0.004569 rad以下、铬酸钙的晶格畸变为0.000094 rad以上且0.004987 rad以下的样品中,能够进一步抑制与燃料极的剥离。 这是因为,互连器的烧结中途即1300℃下的烧成收缩量更接近燃料极的1300℃下的烧成收缩量,从而能够使烧成收缩行为与燃料极一致。</base:Paragraphs>
      </business:EmbodimentsExample>
    </business:EmbodimentsDescription>
    <business:ReferenceSignsList>
      <base:Paragraphs num="0054">100-燃料电池,101-支承基板,102-燃料极,103-电解质层,104-阻隔层,105-空气极,106-互连器,107-集电部。</base:Paragraphs>
    </business:ReferenceSignsList>
  </business:Description>
  <business:Drawings lang="ja" sourceDB="JP">
    <base:Figure num="0001">
      <base:Image id="000005" he="75" wi="78" file="2016124782_000005.TIF" imgContent="drawing" imgFormat="TIFF"/>
    </base:Figure>
    <base:Figure num="0002">
      <base:Image id="000006" he="76" wi="85" file="2016124782_000006.TIF" imgContent="drawing" imgFormat="TIFF"/>
    </base:Figure>
  </business:Drawings>
  <business:Claims lang="ja" dataFormat="original" sourceDB="JP">
    <business:Claim num="0001">
      <business:ClaimText>一种互连器材料,其含有碱土金属中的至少掺杂有钙的铬酸镧作为主成分,并且含有铬酸钙作为副成分,铬酸钙相对于至少掺杂有钙的铬酸镧的质量比为0.004以上,至少掺杂有钙的铬酸镧的晶格畸变为0.000007 rad以上且0.008532 rad以下,铬酸钙的晶格畸变为0.000006 rad以上且0.008080 rad以下。</business:ClaimText>
    </business:Claim>
    <business:Claim num="0002">
      <business:ClaimText>根据权利要求1所述的互连器材料,其中,至少掺杂有钙的铬酸镧的晶格畸变为0.000099 rad以上且0.004569 rad以下,铬酸钙的晶格畸变为0.000094 rad以上且0.004987 rad以下。</business:ClaimText>
    </business:Claim>
  </business:Claims>
</business:PatentDocumentAndRelated>