<?xml version="1.0" encoding="UTF-8"?><!DOCTYPE PatentDocumentAndRelated  SYSTEM '/DTDS/ExternalStandards/ipphdb-entities.dtd' []><business:PatentDocumentAndRelated xmlns:base="http://www.sipo.gov.cn/XMLSchema/base" xmlns:business="http://www.sipo.gov.cn/XMLSchema/business" xmlns:m="http://www.w3.org/1998/Math/MathML" xmlns:tbl="http://oasis-open.org/specs/soextblx" xmlns:xsi="http://www.w3.org/2001/XMLSchema-instance" xsi:schemaLocation="http://www.sipo.gov.cn/XMLSchema/business /DTDS/PatentDocument/Elements/OtherElements.xsd" xsdVersion="V2.2.1" file="JP102016000517238JP00020165199920AFULJA20160711JP00S.XML" dateProduced="20160812" status="C" lang="ja" country="JP" docNumber="2016519992" kind="A" datePublication="20160711">
  <business:BibliographicData lang="ja" country="JP">
    <business:PublicationReference dataFormat="standard" sequence="1">
      <base:DocumentID>
        <base:WIPOST3Code>JP</base:WIPOST3Code>
        <base:DocNumber>2016519992</base:DocNumber>
        <base:Kind>A</base:Kind>
        <base:Date>20160711</base:Date>
      </base:DocumentID>
    </business:PublicationReference>
    <business:PublicationReference dataFormat="original" sourceDB="JP" sequence="1">
      <base:DocumentID>
        <base:WIPOST3Code>JP</base:WIPOST3Code>
        <base:DocNumber>2016519992</base:DocNumber>
        <base:Kind>A</base:Kind>
        <base:Date>20160711</base:Date>
      </base:DocumentID>
    </business:PublicationReference>
    <business:PlainLanguageDesignation lang="ja">公表特許公報(A)</business:PlainLanguageDesignation>
    <business:ApplicationReference applType="10" dataFormat="standard" sequence="1">
      <base:DocumentID>
        <base:WIPOST3Code>JP</base:WIPOST3Code>
        <base:DocNumber>102016000517238</base:DocNumber>
        <base:Date>20140528</base:Date>
      </base:DocumentID>
    </business:ApplicationReference>
    <business:ApplicationReference applType="10" dataFormat="original" sequence="1" sourceDB="JP">
      <base:DocumentID>
        <base:WIPOST3Code>JP</base:WIPOST3Code>
        <base:DocNumber>2016517238</base:DocNumber>
        <base:Date>20140528</base:Date>
      </base:DocumentID>
    </business:ApplicationReference>
    <business:PriorityDetails>
      <business:Priority kind="international" dataFormat="standard" sequence="1">
        <base:WIPOST3Code>EP</base:WIPOST3Code>
        <base:DocNumber>102013000170423</base:DocNumber>
        <base:Date>20130604</base:Date>
      </business:Priority>
      <business:Priority kind="international" dataFormat="original" sourceDB="JP" sequence="1">
        <base:WIPOST3Code>EP</base:WIPOST3Code>
        <base:DocNumber>13170423.1</base:DocNumber>
        <base:Date>20130604</base:Date>
      </business:Priority>
    </business:PriorityDetails>
    <business:ClassificationIPCRDetails>
      <business:ClassificationIPCR sequence="1">
        <business:IPCVersionDate>20060101</business:IPCVersionDate>
        <business:ClassificationLevel>A</business:ClassificationLevel>
        <business:Section>A</business:Section>
        <business:MainClass>47</business:MainClass>
        <business:Subclass>J</business:Subclass>
        <business:MainGroup>37</business:MainGroup>
        <business:Subgroup>06</business:Subgroup>
        <business:SymbolPosition>F</business:SymbolPosition>
        <business:ClassificationValue>I</business:ClassificationValue>
        <base:ActionDate>
          <base:Date>20160613</base:Date>
        </base:ActionDate>
        <business:GeneratingOffice>
          <base:WIPOST3Code>JP</base:WIPOST3Code>
        </business:GeneratingOffice>
        <business:ClassificationStatus>B</business:ClassificationStatus>
        <business:ClassificationDataSource>H</business:ClassificationDataSource>
        <base:Text>A47J  37/06        20060101AFI20160613BHJP        </base:Text>
      </business:ClassificationIPCR>
      <business:ClassificationIPCR sequence="2">
        <business:IPCVersionDate>20060101</business:IPCVersionDate>
        <business:ClassificationLevel>A</business:ClassificationLevel>
        <business:Section>F</business:Section>
        <business:MainClass>24</business:MainClass>
        <business:Subclass>C</business:Subclass>
        <business:MainGroup>1</business:MainGroup>
        <business:Subgroup>00</business:Subgroup>
        <business:SymbolPosition>L</business:SymbolPosition>
        <business:ClassificationValue>I</business:ClassificationValue>
        <base:ActionDate>
          <base:Date>20160613</base:Date>
        </base:ActionDate>
        <business:GeneratingOffice>
          <base:WIPOST3Code>JP</base:WIPOST3Code>
        </business:GeneratingOffice>
        <business:ClassificationStatus>B</business:ClassificationStatus>
        <business:ClassificationDataSource>H</business:ClassificationDataSource>
        <base:Text>F24C   1/00        20060101ALI20160613BHJP        </base:Text>
      </business:ClassificationIPCR>
    </business:ClassificationIPCRDetails>
    <business:JPClassification>
      <business:FI type="main">A47J37/06 361</business:FI>
      <business:FI type="secondary">F24C1/00 Z</business:FI>
      <business:FI type="secondary">F24C1/00 360A</business:FI>
      <business:FClass>
        <business:FTerm>4B040AA02</business:FTerm>
      </business:FClass>
      <business:FClass>
        <business:FTerm>4B040AA08</business:FTerm>
      </business:FClass>
      <business:FClass>
        <business:FTerm>4B040AE13</business:FTerm>
      </business:FClass>
      <business:FClass>
        <business:FTerm>4B040CA05</business:FTerm>
      </business:FClass>
      <business:FClass>
        <business:FTerm>4B040CA09</business:FTerm>
      </business:FClass>
      <business:FClass>
        <business:Theme>4B040</business:Theme>
      </business:FClass>
    </business:JPClassification>
    <business:InventionTitle lang="ja" dataFormat="original" sourceDB="JP">空气喷射</business:InventionTitle>
    <business:Parties>
      <business:ApplicantDetails>
        <business:Applicant sequence="1" dataFormat="original" sourceDB="JP">
          <base:AddressBook lang="ja">
            <base:Name>コーニンクレッカ  フィリップス  エヌ  ヴェ</base:Name>
            <base:RegisteredNumber>590000248</base:RegisteredNumber>
            <base:Address>
              <base:AddressLine>0</base:AddressLine>
              <base:AddressMailCode>0</base:AddressMailCode>
              <base:PostBox>0</base:PostBox>
              <base:AddressRoom>0</base:AddressRoom>
              <base:AddressFloor>0</base:AddressFloor>
              <base:AddressBuilding>0</base:AddressBuilding>
              <base:Street>0</base:Street>
              <base:AddressCity>0</base:AddressCity>
              <base:County>0</base:County>
              <base:City>0</base:City>
              <base:Province>0</base:Province>
              <base:PostCode>0</base:PostCode>
              <base:WIPOST3Code>XP</base:WIPOST3Code>
              <base:Text>オランダ国  5656  アーエー  アインドーフェン  ハイテック  キャンパス  5</base:Text>
            </base:Address>
          </base:AddressBook>
          <base:AddressBook lang="en">
            <base:Name>KONINKLIJKE  PHILIPS  N.V.</base:Name>
            <base:Address>
              <base:AddressLine>0</base:AddressLine>
              <base:AddressMailCode>0</base:AddressMailCode>
              <base:PostBox>0</base:PostBox>
              <base:AddressRoom>0</base:AddressRoom>
              <base:AddressFloor>0</base:AddressFloor>
              <base:AddressBuilding>0</base:AddressBuilding>
              <base:Street>0</base:Street>
              <base:AddressCity>0</base:AddressCity>
              <base:County>0</base:County>
              <base:City>0</base:City>
              <base:Province>0</base:Province>
              <base:PostCode>0</base:PostCode>
              <base:WIPOST3Code>XP</base:WIPOST3Code>
              <base:Text>High  Tech  Campus  5，NL－5656  AE  Eindhoven</base:Text>
            </base:Address>
          </base:AddressBook>
          <business:OrganizationCode createDate="00000000" creator="00">0000000000</business:OrganizationCode>
        </business:Applicant>
      </business:ApplicantDetails>
      <business:InventorDetails>
        <business:Inventor sequence="1" dataFormat="original" sourceDB="JP">
          <base:AddressBook lang="ja">
            <base:Name>デ  ハース，ロヒエル  エンリコ</base:Name>
            <base:Address>
              <base:AddressLine>0</base:AddressLine>
              <base:AddressMailCode>0</base:AddressMailCode>
              <base:PostBox>0</base:PostBox>
              <base:AddressRoom>0</base:AddressRoom>
              <base:AddressFloor>0</base:AddressFloor>
              <base:AddressBuilding>0</base:AddressBuilding>
              <base:Street>0</base:Street>
              <base:AddressCity>0</base:AddressCity>
              <base:County>0</base:County>
              <base:City>0</base:City>
              <base:Province>0</base:Province>
              <base:PostCode>0</base:PostCode>
              <base:WIPOST3Code>XP</base:WIPOST3Code>
              <base:Text>オランダ国，5656  アーエー  アインドーフェン，ハイ・テク・キャンパス  5</base:Text>
            </base:Address>
          </base:AddressBook>
        </business:Inventor>
        <business:Inventor sequence="2" dataFormat="original" sourceDB="JP">
          <base:AddressBook lang="ja">
            <base:Name>パストールス，マルク  アレクサンデル</base:Name>
            <base:Address>
              <base:AddressLine>0</base:AddressLine>
              <base:AddressMailCode>0</base:AddressMailCode>
              <base:PostBox>0</base:PostBox>
              <base:AddressRoom>0</base:AddressRoom>
              <base:AddressFloor>0</base:AddressFloor>
              <base:AddressBuilding>0</base:AddressBuilding>
              <base:Street>0</base:Street>
              <base:AddressCity>0</base:AddressCity>
              <base:County>0</base:County>
              <base:City>0</base:City>
              <base:Province>0</base:Province>
              <base:PostCode>0</base:PostCode>
              <base:WIPOST3Code>XP</base:WIPOST3Code>
              <base:Text>オランダ国，5656  アーエー  アインドーフェン，ハイ・テク・キャンパス  5</base:Text>
            </base:Address>
          </base:AddressBook>
        </business:Inventor>
        <business:Inventor sequence="3" dataFormat="original" sourceDB="JP">
          <base:AddressBook lang="ja">
            <base:Name>ファン  ウィフェレン，レインデルト  ヤネス</base:Name>
            <base:Address>
              <base:AddressLine>0</base:AddressLine>
              <base:AddressMailCode>0</base:AddressMailCode>
              <base:PostBox>0</base:PostBox>
              <base:AddressRoom>0</base:AddressRoom>
              <base:AddressFloor>0</base:AddressFloor>
              <base:AddressBuilding>0</base:AddressBuilding>
              <base:Street>0</base:Street>
              <base:AddressCity>0</base:AddressCity>
              <base:County>0</base:County>
              <base:City>0</base:City>
              <base:Province>0</base:Province>
              <base:PostCode>0</base:PostCode>
              <base:WIPOST3Code>XP</base:WIPOST3Code>
              <base:Text>オランダ国，5656  アーエー  アインドーフェン，ハイ・テク・キャンパス  5</base:Text>
            </base:Address>
          </base:AddressBook>
        </business:Inventor>
        <business:Inventor sequence="4" dataFormat="original" sourceDB="JP">
          <base:AddressBook lang="ja">
            <base:Name>シュリヴァスタヴァ，アダルシュ</base:Name>
            <base:Address>
              <base:AddressLine>0</base:AddressLine>
              <base:AddressMailCode>0</base:AddressMailCode>
              <base:PostBox>0</base:PostBox>
              <base:AddressRoom>0</base:AddressRoom>
              <base:AddressFloor>0</base:AddressFloor>
              <base:AddressBuilding>0</base:AddressBuilding>
              <base:Street>0</base:Street>
              <base:AddressCity>0</base:AddressCity>
              <base:County>0</base:County>
              <base:City>0</base:City>
              <base:Province>0</base:Province>
              <base:PostCode>0</base:PostCode>
              <base:WIPOST3Code>XP</base:WIPOST3Code>
              <base:Text>オランダ国，5656  アーエー  アインドーフェン，ハイ・テク・キャンパス  5</base:Text>
            </base:Address>
          </base:AddressBook>
        </business:Inventor>
        <business:Inventor sequence="5" dataFormat="original" sourceDB="JP">
          <base:AddressBook lang="ja">
            <base:Name>ツァイニッツァー，クリスティアン</base:Name>
            <base:Address>
              <base:AddressLine>0</base:AddressLine>
              <base:AddressMailCode>0</base:AddressMailCode>
              <base:PostBox>0</base:PostBox>
              <base:AddressRoom>0</base:AddressRoom>
              <base:AddressFloor>0</base:AddressFloor>
              <base:AddressBuilding>0</base:AddressBuilding>
              <base:Street>0</base:Street>
              <base:AddressCity>0</base:AddressCity>
              <base:County>0</base:County>
              <base:City>0</base:City>
              <base:Province>0</base:Province>
              <base:PostCode>0</base:PostCode>
              <base:WIPOST3Code>XP</base:WIPOST3Code>
              <base:Text>オランダ国，5656  アーエー  アインドーフェン，ハイ・テク・キャンパス  5</base:Text>
            </base:Address>
          </base:AddressBook>
        </business:Inventor>
        <business:Inventor sequence="6" dataFormat="original" sourceDB="JP">
          <base:AddressBook lang="ja">
            <base:Name>ヴァーミッツァー，ルドルフ</base:Name>
            <base:Address>
              <base:AddressLine>0</base:AddressLine>
              <base:AddressMailCode>0</base:AddressMailCode>
              <base:PostBox>0</base:PostBox>
              <base:AddressRoom>0</base:AddressRoom>
              <base:AddressFloor>0</base:AddressFloor>
              <base:AddressBuilding>0</base:AddressBuilding>
              <base:Street>0</base:Street>
              <base:AddressCity>0</base:AddressCity>
              <base:County>0</base:County>
              <base:City>0</base:City>
              <base:Province>0</base:Province>
              <base:PostCode>0</base:PostCode>
              <base:WIPOST3Code>XP</base:WIPOST3Code>
              <base:Text>オランダ国，5656  アーエー  アインドーフェン，ハイ・テク・キャンパス  5</base:Text>
            </base:Address>
          </base:AddressBook>
        </business:Inventor>
      </business:InventorDetails>
      <business:AgentDetails>
        <business:CustomerNumber>00000</business:CustomerNumber>
        <business:Agent sequence="1" dataFormat="original" sourceDB="JP" repType="agent">
          <base:AddressBook lang="ja">
            <base:Name>伊東  忠重</base:Name>
            <base:RegisteredNumber>100107766</base:RegisteredNumber>
          </base:AddressBook>
        </business:Agent>
        <business:Agent sequence="2" dataFormat="original" sourceDB="JP" repType="agent">
          <base:AddressBook lang="ja">
            <base:Name>伊東  忠彦</base:Name>
            <base:RegisteredNumber>100070150</base:RegisteredNumber>
          </base:AddressBook>
        </business:Agent>
        <business:Agent sequence="3" dataFormat="original" sourceDB="JP" repType="agent">
          <base:AddressBook lang="ja">
            <base:Name>大貫  進介</base:Name>
            <base:RegisteredNumber>100091214</base:RegisteredNumber>
          </base:AddressBook>
        </business:Agent>
      </business:AgentDetails>
    </business:Parties>
    <business:DesignationOfStates>
      <business:DesignationPCT>
        <base:Regional>
          <base:Region>
            <base:WIPOST3Code>AP</base:WIPOST3Code>
          </base:Region>
          <base:WIPOST3Code>BW</base:WIPOST3Code>
          <base:WIPOST3Code>GH</base:WIPOST3Code>
          <base:WIPOST3Code>GM</base:WIPOST3Code>
          <base:WIPOST3Code>KE</base:WIPOST3Code>
          <base:WIPOST3Code>LR</base:WIPOST3Code>
          <base:WIPOST3Code>LS</base:WIPOST3Code>
          <base:WIPOST3Code>MW</base:WIPOST3Code>
          <base:WIPOST3Code>MZ</base:WIPOST3Code>
          <base:WIPOST3Code>NA</base:WIPOST3Code>
          <base:WIPOST3Code>RW</base:WIPOST3Code>
          <base:WIPOST3Code>SD</base:WIPOST3Code>
          <base:WIPOST3Code>SL</base:WIPOST3Code>
          <base:WIPOST3Code>SZ</base:WIPOST3Code>
          <base:WIPOST3Code>TZ</base:WIPOST3Code>
          <base:WIPOST3Code>UG</base:WIPOST3Code>
          <base:WIPOST3Code>ZM</base:WIPOST3Code>
          <base:WIPOST3Code>ZW</base:WIPOST3Code>
        </base:Regional>
        <base:Regional>
          <base:Region>
            <base:WIPOST3Code>EA</base:WIPOST3Code>
          </base:Region>
          <base:WIPOST3Code>AM</base:WIPOST3Code>
          <base:WIPOST3Code>AZ</base:WIPOST3Code>
          <base:WIPOST3Code>BY</base:WIPOST3Code>
          <base:WIPOST3Code>KG</base:WIPOST3Code>
          <base:WIPOST3Code>KZ</base:WIPOST3Code>
          <base:WIPOST3Code>RU</base:WIPOST3Code>
          <base:WIPOST3Code>TJ</base:WIPOST3Code>
          <base:WIPOST3Code>TM</base:WIPOST3Code>
        </base:Regional>
        <base:Regional>
          <base:Region>
            <base:WIPOST3Code>EP</base:WIPOST3Code>
          </base:Region>
          <base:WIPOST3Code>AL</base:WIPOST3Code>
          <base:WIPOST3Code>AT</base:WIPOST3Code>
          <base:WIPOST3Code>BE</base:WIPOST3Code>
          <base:WIPOST3Code>BG</base:WIPOST3Code>
          <base:WIPOST3Code>CH</base:WIPOST3Code>
          <base:WIPOST3Code>CY</base:WIPOST3Code>
          <base:WIPOST3Code>CZ</base:WIPOST3Code>
          <base:WIPOST3Code>DE</base:WIPOST3Code>
          <base:WIPOST3Code>DK</base:WIPOST3Code>
          <base:WIPOST3Code>EE</base:WIPOST3Code>
          <base:WIPOST3Code>ES</base:WIPOST3Code>
          <base:WIPOST3Code>FI</base:WIPOST3Code>
          <base:WIPOST3Code>FR</base:WIPOST3Code>
          <base:WIPOST3Code>GB</base:WIPOST3Code>
          <base:WIPOST3Code>GR</base:WIPOST3Code>
          <base:WIPOST3Code>HR</base:WIPOST3Code>
          <base:WIPOST3Code>HU</base:WIPOST3Code>
          <base:WIPOST3Code>IE</base:WIPOST3Code>
          <base:WIPOST3Code>IS</base:WIPOST3Code>
          <base:WIPOST3Code>IT</base:WIPOST3Code>
          <base:WIPOST3Code>LT</base:WIPOST3Code>
          <base:WIPOST3Code>LU</base:WIPOST3Code>
          <base:WIPOST3Code>LV</base:WIPOST3Code>
          <base:WIPOST3Code>MC</base:WIPOST3Code>
          <base:WIPOST3Code>MK</base:WIPOST3Code>
          <base:WIPOST3Code>MT</base:WIPOST3Code>
          <base:WIPOST3Code>NL</base:WIPOST3Code>
          <base:WIPOST3Code>NO</base:WIPOST3Code>
          <base:WIPOST3Code>PL</base:WIPOST3Code>
          <base:WIPOST3Code>PT</base:WIPOST3Code>
          <base:WIPOST3Code>RO</base:WIPOST3Code>
          <base:WIPOST3Code>RS</base:WIPOST3Code>
          <base:WIPOST3Code>SE</base:WIPOST3Code>
          <base:WIPOST3Code>SI</base:WIPOST3Code>
          <base:WIPOST3Code>SK</base:WIPOST3Code>
          <base:WIPOST3Code>SM</base:WIPOST3Code>
          <base:WIPOST3Code>TR</base:WIPOST3Code>
        </base:Regional>
        <base:Regional>
          <base:Region>
            <base:WIPOST3Code>OA</base:WIPOST3Code>
          </base:Region>
          <base:WIPOST3Code>BF</base:WIPOST3Code>
          <base:WIPOST3Code>BJ</base:WIPOST3Code>
          <base:WIPOST3Code>CF</base:WIPOST3Code>
          <base:WIPOST3Code>CG</base:WIPOST3Code>
          <base:WIPOST3Code>CI</base:WIPOST3Code>
          <base:WIPOST3Code>CM</base:WIPOST3Code>
          <base:WIPOST3Code>GA</base:WIPOST3Code>
          <base:WIPOST3Code>GN</base:WIPOST3Code>
          <base:WIPOST3Code>GQ</base:WIPOST3Code>
          <base:WIPOST3Code>GW</base:WIPOST3Code>
          <base:WIPOST3Code>KM</base:WIPOST3Code>
          <base:WIPOST3Code>ML</base:WIPOST3Code>
          <base:WIPOST3Code>MR</base:WIPOST3Code>
          <base:WIPOST3Code>NE</base:WIPOST3Code>
          <base:WIPOST3Code>SN</base:WIPOST3Code>
          <base:WIPOST3Code>TD</base:WIPOST3Code>
          <base:WIPOST3Code>TG</base:WIPOST3Code>
        </base:Regional>
        <base:National>
          <base:WIPOST3Code>AE</base:WIPOST3Code>
          <base:WIPOST3Code>AG</base:WIPOST3Code>
          <base:WIPOST3Code>AL</base:WIPOST3Code>
          <base:WIPOST3Code>AM</base:WIPOST3Code>
          <base:WIPOST3Code>AO</base:WIPOST3Code>
          <base:WIPOST3Code>AT</base:WIPOST3Code>
          <base:WIPOST3Code>AU</base:WIPOST3Code>
          <base:WIPOST3Code>AZ</base:WIPOST3Code>
          <base:WIPOST3Code>BA</base:WIPOST3Code>
          <base:WIPOST3Code>BB</base:WIPOST3Code>
          <base:WIPOST3Code>BG</base:WIPOST3Code>
          <base:WIPOST3Code>BH</base:WIPOST3Code>
          <base:WIPOST3Code>BN</base:WIPOST3Code>
          <base:WIPOST3Code>BR</base:WIPOST3Code>
          <base:WIPOST3Code>BW</base:WIPOST3Code>
          <base:WIPOST3Code>BY</base:WIPOST3Code>
          <base:WIPOST3Code>BZ</base:WIPOST3Code>
          <base:WIPOST3Code>CA</base:WIPOST3Code>
          <base:WIPOST3Code>CH</base:WIPOST3Code>
          <base:WIPOST3Code>CL</base:WIPOST3Code>
          <base:WIPOST3Code>CN</base:WIPOST3Code>
          <base:WIPOST3Code>CO</base:WIPOST3Code>
          <base:WIPOST3Code>CR</base:WIPOST3Code>
          <base:WIPOST3Code>CU</base:WIPOST3Code>
          <base:WIPOST3Code>CZ</base:WIPOST3Code>
          <base:WIPOST3Code>DE</base:WIPOST3Code>
          <base:WIPOST3Code>DK</base:WIPOST3Code>
          <base:WIPOST3Code>DM</base:WIPOST3Code>
          <base:WIPOST3Code>DO</base:WIPOST3Code>
          <base:WIPOST3Code>DZ</base:WIPOST3Code>
          <base:WIPOST3Code>EC</base:WIPOST3Code>
          <base:WIPOST3Code>EE</base:WIPOST3Code>
          <base:WIPOST3Code>EG</base:WIPOST3Code>
          <base:WIPOST3Code>ES</base:WIPOST3Code>
          <base:WIPOST3Code>FI</base:WIPOST3Code>
          <base:WIPOST3Code>GB</base:WIPOST3Code>
          <base:WIPOST3Code>GD</base:WIPOST3Code>
          <base:WIPOST3Code>GE</base:WIPOST3Code>
          <base:WIPOST3Code>GH</base:WIPOST3Code>
          <base:WIPOST3Code>GM</base:WIPOST3Code>
          <base:WIPOST3Code>GT</base:WIPOST3Code>
          <base:WIPOST3Code>HN</base:WIPOST3Code>
          <base:WIPOST3Code>HR</base:WIPOST3Code>
          <base:WIPOST3Code>HU</base:WIPOST3Code>
          <base:WIPOST3Code>ID</base:WIPOST3Code>
          <base:WIPOST3Code>IL</base:WIPOST3Code>
          <base:WIPOST3Code>IN</base:WIPOST3Code>
          <base:WIPOST3Code>IR</base:WIPOST3Code>
          <base:WIPOST3Code>IS</base:WIPOST3Code>
          <base:WIPOST3Code>JP</base:WIPOST3Code>
          <base:WIPOST3Code>KE</base:WIPOST3Code>
          <base:WIPOST3Code>KG</base:WIPOST3Code>
          <base:WIPOST3Code>KN</base:WIPOST3Code>
          <base:WIPOST3Code>KP</base:WIPOST3Code>
          <base:WIPOST3Code>KR</base:WIPOST3Code>
          <base:WIPOST3Code>KZ</base:WIPOST3Code>
          <base:WIPOST3Code>LA</base:WIPOST3Code>
          <base:WIPOST3Code>LC</base:WIPOST3Code>
          <base:WIPOST3Code>LK</base:WIPOST3Code>
          <base:WIPOST3Code>LR</base:WIPOST3Code>
          <base:WIPOST3Code>LS</base:WIPOST3Code>
          <base:WIPOST3Code>LT</base:WIPOST3Code>
          <base:WIPOST3Code>LU</base:WIPOST3Code>
          <base:WIPOST3Code>LY</base:WIPOST3Code>
          <base:WIPOST3Code>MA</base:WIPOST3Code>
          <base:WIPOST3Code>MD</base:WIPOST3Code>
          <base:WIPOST3Code>ME</base:WIPOST3Code>
          <base:WIPOST3Code>MG</base:WIPOST3Code>
          <base:WIPOST3Code>MK</base:WIPOST3Code>
          <base:WIPOST3Code>MN</base:WIPOST3Code>
          <base:WIPOST3Code>MW</base:WIPOST3Code>
          <base:WIPOST3Code>MX</base:WIPOST3Code>
          <base:WIPOST3Code>MY</base:WIPOST3Code>
          <base:WIPOST3Code>MZ</base:WIPOST3Code>
          <base:WIPOST3Code>NA</base:WIPOST3Code>
          <base:WIPOST3Code>NG</base:WIPOST3Code>
          <base:WIPOST3Code>NI</base:WIPOST3Code>
          <base:WIPOST3Code>NO</base:WIPOST3Code>
          <base:WIPOST3Code>NZ</base:WIPOST3Code>
          <base:WIPOST3Code>OM</base:WIPOST3Code>
          <base:WIPOST3Code>PA</base:WIPOST3Code>
          <base:WIPOST3Code>PE</base:WIPOST3Code>
          <base:WIPOST3Code>PG</base:WIPOST3Code>
          <base:WIPOST3Code>PH</base:WIPOST3Code>
          <base:WIPOST3Code>PL</base:WIPOST3Code>
          <base:WIPOST3Code>PT</base:WIPOST3Code>
          <base:WIPOST3Code>QA</base:WIPOST3Code>
          <base:WIPOST3Code>RO</base:WIPOST3Code>
          <base:WIPOST3Code>RS</base:WIPOST3Code>
          <base:WIPOST3Code>RU</base:WIPOST3Code>
          <base:WIPOST3Code>RW</base:WIPOST3Code>
          <base:WIPOST3Code>SA</base:WIPOST3Code>
          <base:WIPOST3Code>SC</base:WIPOST3Code>
          <base:WIPOST3Code>SD</base:WIPOST3Code>
          <base:WIPOST3Code>SE</base:WIPOST3Code>
          <base:WIPOST3Code>SG</base:WIPOST3Code>
          <base:WIPOST3Code>SK</base:WIPOST3Code>
          <base:WIPOST3Code>SL</base:WIPOST3Code>
          <base:WIPOST3Code>SM</base:WIPOST3Code>
          <base:WIPOST3Code>ST</base:WIPOST3Code>
          <base:WIPOST3Code>SV</base:WIPOST3Code>
          <base:WIPOST3Code>SY</base:WIPOST3Code>
          <base:WIPOST3Code>TH</base:WIPOST3Code>
          <base:WIPOST3Code>TJ</base:WIPOST3Code>
          <base:WIPOST3Code>TM</base:WIPOST3Code>
          <base:WIPOST3Code>TN</base:WIPOST3Code>
          <base:WIPOST3Code>TR</base:WIPOST3Code>
          <base:WIPOST3Code>TT</base:WIPOST3Code>
          <base:WIPOST3Code>TZ</base:WIPOST3Code>
          <base:WIPOST3Code>UA</base:WIPOST3Code>
          <base:WIPOST3Code>UG</base:WIPOST3Code>
          <base:WIPOST3Code>US</base:WIPOST3Code>
        </base:National>
      </business:DesignationPCT>
    </business:DesignationOfStates>
    <business:PCTOrRegionalApplicationData>
      <base:DocumentID>
        <base:DocNumber>EP2014061006</base:DocNumber>
        <base:Date>20140528</base:Date>
      </base:DocumentID>
    </business:PCTOrRegionalApplicationData>
    <business:PCTOrRegionalPublishingData>
      <base:DocumentID>
        <base:DocNumber>WO2014195192</base:DocNumber>
        <base:Date>20141211</base:Date>
      </base:DocumentID>
    </business:PCTOrRegionalPublishingData>
    <business:SpecificBibliographicData>
      <business:OriginalKindCode>T</business:OriginalKindCode>
    </business:SpecificBibliographicData>
    <business:StatisticalInformation>
      <base:TotalPageCount>24</base:TotalPageCount>
    </business:StatisticalInformation>
  </business:BibliographicData>
  <business:Abstract dataFormat="original" lang="ja" sourceDB="JP">
    <base:Paragraphs>本发明涉及食品的烹调。 为了提供用于用热空气烹饪食物的装置,提供了用于烹饪食物的装置（10）,其包括食物烹饪室（12）、空气移动装置（14）、加热装置（16）和空气引导装置（18）。 食物制备室由容器结构（22）提供,容器结构（22）至少部分地围绕用于接收待制备的食物的接收体积（24）,容器结构具有侧壁（26）和底壁（28）,其中一个侧壁和/或底壁是可透气的并且包括用于热空气进入接收体积的空气入口开口（30）,容器结构具有空气释放开口（32）。 加热装置构造成加热由空气移动装置提供的空气流中的空气。 空气引导装置提供空气管道装置（34）,该空气管道装置从排气开口经由加热装置和空气移动装置到达空气入口开口。 空气移动装置是具有空气入口38和空气出口40的风扇36,风扇设置在食物制备室的侧面。 加热装置布置在从接收体积不可见的位置,并且在装置的操作期间,主要通过由空气移动装置和加热装置提供的热空气的流通来烹饪食物。</base:Paragraphs>
    <business:AbstractFigure>
      <base:Figure num="0001">
        <base:Image id="000002" he="50" wi="69" file="2016519992_000002.TIF" imgFormat="TIFF" imgContent="drawing"/>
      </base:Figure>
    </business:AbstractFigure>
  </business:Abstract>
  <business:Description dataFormat="original" sourceDB="JP">
    <business:TechnicalField>
      <base:Paragraphs num="0001">本发明涉及食物的烹饪,特别是涉及用于烹饪食物的装置和用于烹饪食物的方法。</base:Paragraphs>
    </business:TechnicalField>
    <business:BackgroundArt>
      <base:Paragraphs num="0002">用于烹饪食物的设备的示例是飞利浦空气煎锅,其是能够在热空气中烹饪食物（例如炸鸡或鸡肉）的设备。 为了加热食物以制备食物,热空气流在食物上被驱动以加热食物,并且分别为了加热目的被吹过食物容纳体积。 例如,这种设备可以在家庭环境中使用。 对于优化的食物制备过程,通过整个食物容纳体积的尽可能高的空气流量是优选的。 高流速确保了相对短的烹饪时间和高的食物质量。 DE 10 200 4 015 015 A1描述了一种用于在热空气中烹饪食物的装置。 然而,已经表明存在对更短的烹饪时间和更高的食物质量的需求,并且因此存在对更高的空气流速的持续增长的需求。</base:Paragraphs>
    </business:BackgroundArt>
    <business:CitationList>
      <business:PatentDocumentation>
        <base:Paragraphs num="0003">           <business:ApplicationCitation num="0001">
            <base:Text>WO  2012／032449  A1</base:Text>
          </business:ApplicationCitation> </base:Paragraphs>
      </business:PatentDocumentation>
    </business:CitationList>
    <business:InventionSummary>
      <business:TechnicalProblem>
        <base:Paragraphs num="0004">可能需要提供一种用于在热空气中烹饪食物的装置,该装置具有改进的流动特性。</base:Paragraphs>
      </business:TechnicalProblem>
      <business:TechnicalSolution>
        <base:Paragraphs num="0005">本发明的目的通过独立权利要求的主题来解决,其中其他实施例被并入从属权利要求中。 应当注意的是,下面描述的本发明的各方面也适用于用于烹饪食物的装置以及用于烹饪食物的方法。</base:Paragraphs>
        <base:Paragraphs num="0006">根据本发明,提供了一种用于烹饪食物的装置,该装置包括食物烹饪室、空气移动装置、加热装置和空气引导装置。 食物制备室由容器结构提供,该容器结构至少部分地围绕用于接收待通过热空气流通制备的食物的接收体积,该容器结构具有侧壁和底壁。 侧壁和/或底壁中的一个是可透气的并且包括用于热空气进入接收体积的空气入口开口。 容器结构还具有空气释放开口。 加热装置构造成加热由空气移动装置提供的空气流中的空气。 空气引导装置提供从排气开口经由加热装置和空气移动装置到空气入口开口的空气管道装置。 空气移动装置是具有空气入口和空气出口的风扇。 风扇设置在食物制备室的侧面。</base:Paragraphs>
        <base:Paragraphs num="0007">通过在食物制备室的侧面设置风扇,通过将风扇布置在空气入口开口附近来改善气流路径,其中需要最强的气流以使热空气适当且分散地进入待制备的食物中。</base:Paragraphs>
        <base:Paragraphs num="0008">表述“空气引导装置提供空气管道装置”涉及允许循环空气流的空气管道。 这可以由特定的空气流动路径或空气导管提供。 然而,替代地或附加地,这也可以由围绕不同装置和/或元件的装置的壳体提供。 例如,空气引导装置在空气置换装置附近具有空气管道段,以将空气从空气置换装置引导到食物制备室并从食物制备室返回到空气置换装置。 在其他示例中,相当强的风扇（诸如空气移动装置）设置在壳体中以提供循环气流,并且壳体提供空气管道。 例如,空气移动装置和食物制备室被布置成使得食物制备室的旁通气流被阻止,例如,食物制备室被布置成靠近壳体的内侧壁,空气移动装置也被布置成靠近壳体的内侧壁,并且空气移动装置和食物制备室被布置成彼此靠近。</base:Paragraphs>
        <base:Paragraphs num="0009">表述“热空气的流通”是指向待由热空气烹饪的食物供应热量。 空气不仅到达食物堆的上表面,而且还到达食物堆的内部空间,例如法式炸薯条堆。 这种法式炸薯条在英语中被称为薯条（chips）,在法语中被称为炸薯条（frites）,在德语中被称为炸薯条（Pommes Frites）。 表述“热空气的流通流”涉及通过食物的热空气,即,食物堆,也称为食物堆或食物块。 因此,热空气不仅围绕食物的外边界移动,而且实际上直接加热,即,将热量直接传递到外边界区域内的位置,例如食物部分的主要部分内。 当然,除了法式油炸食品之外,还提供了具有类似结构的其他食品,即呈多个单件形式或呈堆叠、整块或堆叠形式的食品。 因此,“热空气的流通”不仅提供了整个食物室的热分布,而且还提供了到食物内部的热传递。</base:Paragraphs>
        <base:Paragraphs num="0010">在示例中,气流以高速、特别是以高流速供应到食物制备室。 例如,供给约最小20l/sec的空气流量。</base:Paragraphs>
        <base:Paragraphs num="0011">在示例中,气流路径设置有横截面的最小数量的变化。 例如,提供了一种气流路径,其横截面从空气离开通风装置的点到空气再次进入通风装置的点仅在高达约40%的范围内变化。 在其他示例中,提供了高达约20%的横截面变化。 应避免喷嘴。</base:Paragraphs>
        <base:Paragraphs num="0012">在示例中,布置没有喷嘴的气流路径。</base:Paragraphs>
        <base:Paragraphs num="0013">在示例中,用于烹饪食物的装置主要通过热空气向待烹饪的食物提供热量。 在示例中,单向加热由热空气提供,即,热空气是作用于或影响食物制备室中的食物的唯一热源。</base:Paragraphs>
        <base:Paragraphs num="0014">由容器结构提供的食物制备室可以具有插入件,例如具有网状结构的篮子结构,用于以方便的方式插入食物,并且还用于在制备之后再次从设备中取出制备的食物。 容器结构也可以是可移除的,以用于充排目的以及用于清洁目的。</base:Paragraphs>
        <base:Paragraphs num="0015">根据示例,设置具有空气吸入侧和空气吹出侧的风扇作为空气移动装置。 在使用中,空气在空气吹送侧以平均吹送方向吹送,平均吹送方向包括相对于水平和垂直两者的倾斜角度。</base:Paragraphs>
        <base:Paragraphs num="0016">这提供的优点是,降低了从风扇引导空气流的要求,因为空气流已经具有倾斜角度并且例如不垂直地撞击下侧。 这也是有利的,因为空气吹送侧上的空气流可以相对于循环空气流路径表现出最大空气速度。</base:Paragraphs>
        <base:Paragraphs num="0017">平均吹出方向可以被视为通风的（即运动的）空气的主要或主要吹出方向。 然而,由于空气流的实际吹送特性不是直接可见的,因此要注意以下几点：在非常常见的示例中,风扇具有至少一个用于使空气运动的旋转部分,诸如旋转叶片,因此提供旋转轴线。 诸如叶片等的空气移动元件的旋转导致相应的吹出方向。 例如,空气移动装置可以被提供为轴流风扇,其中平均吹气方向与旋转轴线对准,例如平行于旋转轴线。 作为另一示例,空气移动装置可以被提供为离心式风扇,也称为径向风扇,其中平均吹出方向与旋转叶片的切线对齐,其中切线垂直于旋转轴线。 因此,旋转轴线的方向也确定了相对于气流的基本方向,例如,在轴流式风扇的情况下平行于气流,或者在离心式风扇的情况下垂直于气流。</base:Paragraphs>
        <base:Paragraphs num="0018">在示例中,旋转轴线相对于水平方向和/或垂直方向以倾斜角度提供。 根据示例,风扇是在具有轴向空气入口和径向空气出口的风扇壳体内部的离心式风扇。 离心式风扇具有在旋转平面中旋转的叶片,该旋转平面包括相对于水平和垂直两者的倾斜角度。</base:Paragraphs>
        <base:Paragraphs num="0019">这提供了以下优点：离开风扇的空气需要比在风扇内进行的空气引导件更少的偏差或空气引导件。 换句话说,风扇内的气流方向的大致垂直变化被并入气流路径中,使得从食物制备室朝向风扇的气流包括大于90°的角度,并且离开风扇的空气在被施加到食物制备室之前也表现出大于90°的方向变化。 气流路径的最陡弯曲发生在风扇本身内。 由于突然弯曲意味着对气流的流动阻力增加,因此在具有高流速的流动区域中提供大于90°的角度意味着关于使流动阻力最小化以使流动最大化的优点。 风扇内部的相当急剧的弯曲或甚至最急剧的弯曲的设置考虑到流动无论如何都受到这里的风扇叶片的影响。</base:Paragraphs>
        <base:Paragraphs num="0020">根据示例,倾斜角度包括在约10°至80°的范围内的相对于水平的角度。 例如,提供约45°的角度。</base:Paragraphs>
        <base:Paragraphs num="0021">应当注意,本领域技术人员也将理解,可以从这些方向提供不同的解决方案,并且该解决方案提供了结构化的空气引导装置。</base:Paragraphs>
        <base:Paragraphs num="0022">倾斜布置还提供了紧凑壳体的优点。</base:Paragraphs>
        <base:Paragraphs num="0023">根据另一示例,第一线由旋转轴线限定,第二线在旋转平面中垂直于第一线布置,并且第三线垂直于底壁并穿过底壁的中心。 第一线、第二线和第三线布置在一个平面中并形成三角形。 三角形的内圆布置在设备的壳体结构内部。 第一线和第二线具有布置在壳体结构的高度的中间区域中的交叉点。 内圆具有最大直径。</base:Paragraphs>
        <base:Paragraphs num="0024">根据另一示例,该设备是桌面设备。 术语“桌面设备”是指适用于家庭应用的设备,该设备可以放置在厨房或桌子的不同工作表面上,或者可以放置在用于家庭应用的架子或柜子上。 桌面设备可以手动移动并由一个人带到不同的位置。 对于家庭应用,设备占据的体积被限制为尽可能小的尺寸。 在示例中,桌面设备与便携式设备相关联。</base:Paragraphs>
        <base:Paragraphs num="0025">根据另一示例,加热装置布置在从接收体积不可见的位置。</base:Paragraphs>
        <base:Paragraphs num="0026">通过将加热装置布置在从接收体积不可见的位置,阻止了用于热辐射的直接路径。 因此,对流是将热量传递到待烹饪的食物的主要来源。 换句话说,与更高的空气流相结合,可以提供具有增加的功率的加热器,即,具有向空气流的更高的热传递能力的加热器,以用于改进的热传递。 由于加热器功率由气流（l/s）确定,因此较高的气流意味着可以使用较高功率的加热器,而不会在食物体积的下部和上部之间产生太大的温度差。 由于来自顶部的辐射被阻挡,即被阻挡,因此不再需要实现辐射和对流之间的精确平衡。 因此,即使用户用食物过度填充设备并导致较低的气流,食物的质量也低于在正常填充水平下烹饪时的质量,但是与食物暴露于加热器辐射时相比,提供了更好的食物质量。 即使在导致较高加热器温度的较低流速的情况下,加热器在较低流速下冷却较少,但是通过提供对流作为食物的唯一热源来确保适当的热分布。 例如,可以通过温度测量装置测量携带对流热的空气的温度。 在流速降低并且因此加热器温度增加的情况下,如果空气温度过高,即达到临界水平,则温度测量装置可以关闭加热器。 在加热器处于加热器的直接视线中的情况下,较高的加热器温度仅部分地导致较高的空气温度,因为仅一部分加热器能量通过对流被输送。 特别地,在食物仍然相对较冷（在过程开始时）的情况下,不会检测到过度暴露于辐射,因为食物冷却气流。 通过将加热装置布置在接收体积的外侧,防止了这种情况。 因为不同类型的食物具有不同的可能的通过速率,所以这也考虑了烹饪越来越多变化范围的食物的需要。 由于辐射作为热源被排除,因此不再需要辐射和对流的适当平衡。 因此,还考虑在加热器的寿命期间加热器的辐射率的变化。 如果加热器的功率降低,则仅需要增加烹饪食物的时间。 然而,由于不需要监测和调整辐射和对流的适当平衡,因此优化了食物质量。</base:Paragraphs>
        <base:Paragraphs num="0027">加热器仅或至少大部分以对流的形式（即,以热空气流的形式,而不是通过辐射）提供热能。 因此,即使在不同的食物类型和数量下,热空气形式的热源也提供了良好和均匀的食物质量,并且还提供了短的或至少最小化的烹饪时间。 因此,可以烹饪越来越多的食物。</base:Paragraphs>
        <base:Paragraphs num="0028">表述“在不可见的地方”还包括其中加热器被放置在不可见的地方（例如,70%或更多）的布置。 在示例中,90%是不可见的。</base:Paragraphs>
        <base:Paragraphs num="0029">例如,加热装置包括具有供热表面的一个或多个加热元件。 供热表面的一些部分朝向食物制备室,即在食物制备室的方向上。 以下是指“不可见的地方”：当从食物制备室观察时,面向食物制备室的供热表面的大部分是不可见的,即被遮挡。 例如,如果用光源替换加热器,则从食物制备室仅可以看到光供应表面的很少的光,或者没有光。</base:Paragraphs>
        <base:Paragraphs num="0030">例如,由加热装置提供的热量被屏蔽或阻挡以防止朝向食物的辐射。 这提供了一种布置,其中热量（即热能）仅通过热空气（或至少在最大程度上）传递到食物。 当然,热空气也可以加热外壳或侧壁,然后这些表面通过辐射将热量传递到食物。 然而,这种热传递可以与热空气的热传递相关联地忽略不计。 例如,经由高音空气（即,经由对流）的热传递被提供为使得到食物的热能传递的至少70%。 在示例中,至少80,例如至少90或95%的热量由热空气提供。</base:Paragraphs>
        <base:Paragraphs num="0031">表述“在不可见的地方”涉及热辐射的直接路径。 例如,热辐射路径独立于光学路径,即,独立于直接（可见）光线。 例如,辐射热可以通过过滤器或空气分配元件,而透过过滤器不可见,即,过滤器是不透明的。 根据本发明的一个示例,加热器被布置成使得设置成用于通过穿过热表面的空气流（由诸如通风装置或风扇的空气移动装置推动的空气流）的热对流的加热元件,例如,使得由热表面辐射的热量也提供辐射。 然而,提供了辐射热不影响食物容器中的食物的方式。 在示例中,该装置可以包括将加热元件布置在食物容器的侧面上,即,邻近容器的侧壁的外侧。 所述装置可以包括用于防止辐射的热传递的屏蔽元件。 例如,容器侧壁可以布置在加热元件与容器体积的布置成接收食物的部分之间。 在其他示例中,单独的保护元件提供对来自加热元件的热辐射的屏蔽。 在其他示例中,加热元件被布置成使得它们仅在远离食物的方向上辐射热量。</base:Paragraphs>
        <base:Paragraphs num="0032">根据示例,加热装置位于食物制备室的侧面。</base:Paragraphs>
        <base:Paragraphs num="0033">根据另一示例,所述空气管道装置具有多个引导部分,在所述多个引导部分中,气流方向被改变。 第一引导部分设置在空气置换装置之后的下游,并且第二引导部分设置在空气置换装置之前的上游。 第一引导部分提供比第二引导部分更小程度的气流方向变化。</base:Paragraphs>
        <base:Paragraphs num="0034">根据另一示例,具有收集体积的收集装置设置在食物制备室下方,用于收集残余物。</base:Paragraphs>
        <base:Paragraphs num="0035">因此,例如,它被提供用于收集设备的可移除盘的特定位置的油和碎片。 来自食物的油和碎片被离开风扇系统的热空气吹到该位置。 在烹饪过程之后,消费者可以容易地访问该位置以进行清洁。 这可以导致更频繁的清洁,并且防止油由于重复加热而粘在表面上。 此外,它还防止装置中最重要的气流路径的阻塞。 这支持设备在使用期间的均匀性能。 另一个方面是油和小块体积可以位于空气温度足够低的位置,以防止在烹饪过程期间冒烟。</base:Paragraphs>
        <base:Paragraphs num="0036">可以清楚地注意到,根据另一方面,收集设备结合上述特征提供,但是没有例如空气移动设备的倾斜布置或加热设备的不可见布置。 例如,提供了一种用于烹饪食物的装置,该装置包括食物烹饪室、空气移动装置、加热装置和空气引导装置。 食物制备室由容器结构提供,该容器结构至少部分地围绕接收体积,该接收体积用于接收要通过热空气的流通流制备的食物。 容器结构具有侧壁和底壁。 侧壁和/或底壁中的一个是可透气的,并且提供用于热空气进入接收体积的空气入口开口。 容器结构还具有空气释放开口。 加热装置构造成加热由空气移动装置提供的空气流中的空气。 空气引导装置提供从排气开口经由加热装置和空气移动装置到空气入口开口的空气管道装置。 根据另一方面,具有收集体积的收集装置设置在食物制备结构下方,用于收集残余物,例如油和碎片。</base:Paragraphs>
        <base:Paragraphs num="0037">根据另一示例,设置有空气引导元件,该空气引导元件将容器结构下方的水平空气流沿朝向空气入口开口的向上方向引导。 收集装置在背离水平气流的一侧上布置在空气引导元件的旁边。</base:Paragraphs>
        <base:Paragraphs num="0038">根据另一示例,空气分配管道设置在底壁中的空气入口开口下方。 空气引导件设置为在空气分配管道的下表面上在空气入口开口下方布置的脊部。 空气引导件以相对于空气出口的吹出方向的竖直方向倾斜的方式布置,使得在空气入口开口下方提供均匀分布的空气流。</base:Paragraphs>
        <base:Paragraphs num="0039">例如,脊部在空气分配管道的横截面上延伸。 在示例中,脊部在横截面的至少三分之一上延伸,例如在一个区段中或甚至在远端区段中延伸。 在另一示例中,脊部在横截面的至少一半上延伸。 在另一示例中,脊部在整个横截面上延伸。</base:Paragraphs>
        <base:Paragraphs num="0040">倾斜或旋转的空气引导件将来自风扇系统的不均匀气流转换成均匀分布在例如食物篮的底表面上的气流,例如用于接收油炸。 必须注意的是,在横截面视图中,旋转是不可见的。</base:Paragraphs>
        <base:Paragraphs num="0041">根据另一方面,可以清楚地注意到,空气分配管道结合上述特征提供,但是没有例如空气移动装置的倾斜布置或加热装置的不可见布置。 例如,提供了一种用于烹饪食物的装置,该装置包括食物烹饪室、空气移动装置、加热装置和空气引导装置。 食物制备室由容器结构提供,该容器结构至少部分地围绕接收体积,该接收体积用于接收要通过热空气的流通流制备的食物。 容器结构具有侧壁和底壁。 侧壁和/或底壁中的一个是可透气的,并且提供用于热空气进入接收体积的空气入口开口。 容器结构还具有空气释放开口。 加热装置构造成加热由空气移动装置提供的空气流中的空气。 空气引导装置提供从排气开口经由加热装置和空气移动装置到空气入口开口的空气管道装置。 根据另一方面,空气分配管道设置在底壁中的空气入口开口下方,并且空气引导件设置为位于空气入口开口下方的空气分配管道的下表面上的脊部。 空气引导件以相对于空气出口的吹出方向的垂直方向倾斜的方式布置,使得在空气入口开口下方提供均匀分布的空气流。</base:Paragraphs>
        <base:Paragraphs num="0042">例如,脊部在空气分配管道的横截面上延伸。 在示例中,脊部在横截面的至少三分之一上延伸,例如在一个区段中或甚至在远端区段中延伸。 在另一示例中,脊部在横截面的至少一半上延伸。 在另一示例中,脊部在整个横截面上延伸。</base:Paragraphs>
        <base:Paragraphs num="0043">根据另一示例,在空气出口和设置在底壁的空气入口开口下方的空气分配区域之间设置气流扩散器。 流扩散器被设置为具有横向于空气通过方向的减小的横截面的管道段,以补偿空气出口的不对称空气输出。</base:Paragraphs>
        <base:Paragraphs num="0044">根据另一方面,清楚地注意到,流扩散器结合上述特征提供,但是没有例如空气移动装置的倾斜布置或加热装置的不可见布置。 例如,提供了一种用于烹饪食物的装置,该装置包括食物烹饪室、空气移动装置、加热装置和空气引导装置。 食物制备室由容器结构提供,该容器结构至少部分地围绕接收体积,该接收体积用于接收要通过热空气的流通流制备的食物。 容器结构具有侧壁和底壁。 侧壁和/或底壁中的一个是可透气的,并且提供用于热空气进入接收体积的空气入口开口。 容器结构具有空气释放开口。 加热装置构造成加热由空气移动装置提供的空气流中的空气。 空气引导装置提供从排气开口经由加热装置和空气移动装置到空气入口开口的空气管道装置。 根据另一方面,在空气出口和设置在底壁的空气入口开口下方的空气分配区域之间设置气流扩散器。 流扩散器被设置为具有横向于空气通过方向的减小的横截面的管道段,以补偿空气出口的不对称空气输出。</base:Paragraphs>
        <base:Paragraphs num="0045">在另一个示例中,用于倾斜位置的空气管道壁是外部或最低位置的空气管道壁,因为空气管道壁还支持空气流在有益方向上的弯曲。 空气管道将成为空气弯曲系统的一部分,并且符合保持总弯曲小于360°的策略。</base:Paragraphs>
        <base:Paragraphs num="0046">关于热空气的流动方向的“弯曲”和“弯曲角度”的表述涉及气流方向相对于直线方向的偏转或角度变化。 例如,在没有弯曲的情况下,即在气流方向没有变化的情况下,该角度被称为0°的角度,并且具有5°的角度的弯曲与气流方向在侧向方向上的轻微变化相关联。 如果空气流被引导成使得空气流方向以直角方式改变,则这被称为90°的弯曲角,并且以U形转弯的方式偏转（换言之,以反向方式）的空气引导是180°的弯曲角。</base:Paragraphs>
        <base:Paragraphs num="0047">根据本发明,还提供了一种烹饪食物的方法,该方法包括以下步骤： 在第一提供步骤中,将食物供应到食物制备室,所述食物制备室由容器结构提供,所述容器结构至少部分地包围用于接收待制备的食物的接收体积。 在第二提供步骤中,将热空气的流通流提供给食物制备室。 热空气的流通流由空气移动装置和加热装置提供。 循环空气流由空气引导装置提供,该空气引导装置提供空气管道装置,该空气管道装置从容器结构的排放开口经由加热装置和空气移位装置到容器结构的空气入口开口。 设置具有空气入口和空气出口的风扇用于空气的运动。 风扇设置在食物制备室的侧面。</base:Paragraphs>
        <base:Paragraphs num="0048">根据本发明的一个方面,提供了一种空气飞轮,其中流动路径的阻力被最小化,并且旨在使空气再循环系统中的所有弯曲角度的最小总和高达360°。 在一个示例中,风扇壳体的出口被设置成使得离开风扇的空气在到达将气流引导到食物室的另一个空气引导件之前必须具有相对平滑的弯曲或平滑的空气偏转。 由于这些位置处的高空气速度,由湍流和摩擦引起的损失被最小化,导致相对低的空气阻力,因此导致更高的总流量和更大的空气通过空气引导件进入食物的动量。 在示例中,风扇被布置成使得空气在进入风扇之前必须改变方向,但是这不是关键的,因为在该位置处,空气速度至少略低,并且所谓的压力或抽吸。 例如,与通过这种弯曲部吹送空气相比,在该弯曲部中使用抽吸以及横截面的变化可能是优选的,因为横截面的变化可能导致更少的湍流和损失。</base:Paragraphs>
        <base:Paragraphs num="0049">根据本发明的另一方面,提供加热器,使得从加热器直接辐射到腔室内的食物上的热量被移除和阻止。 因此,加热器仅将热量传递到通过加热器的空气流中,使得空气流是用于加热食物制备室内的食物的唯一热源。 因此,还消除了辐射热和对流热的潜在不平衡,这意味着促进了热能和空气通风或空气流供应的调节。</base:Paragraphs>
        <base:Paragraphs num="0050">参考下文描述的实施例,本发明的这些和其他方面将变得显而易见,并且将参考下文描述的实施例进行解释。</base:Paragraphs>
      </business:TechnicalSolution>
    </business:InventionSummary>
    <business:DrawingsDescription>
      <base:Paragraphs num="0051">下面将参考以下附图描述本发明的示例性实施例,其中：<base:FigureReference num="0001">图0001示出了用于烹饪食物的装置的示例的示意性横截面。</base:FigureReference><base:FigureReference num="0002">图0002示出了具有图2A的蜗壳内的离心风扇的第一示例、具有图2B的轴流风扇的第二示例以及图2C的横流式鼓风机的第三示例的用于烹饪食物的设备的示意性横截面的另一示例。</base:FigureReference><base:FigureReference num="0003">图0003示意性地示出了用于烹饪食物的设备的另一示例的横截面。</base:FigureReference><base:FigureReference num="0004">图4A、图4B和图4C示出了用于烹饪食物的装置的示意性横截面的几何关系的示例。</base:FigureReference><base:FigureReference num="0005">图0005示出了用于烹饪食物的装置的另一示意性横截面示例,该装置具有设置在从接收体积不可见的位置处的加热装置。</base:FigureReference><base:FigureReference num="0006">图0006示出了用于烹饪食物的设备的另一示例的示意性横截面,其中收集设备位于食物烹饪室下方。</base:FigureReference><base:FigureReference num="0007">图0007以图7A的示意性截面和图7B的透视图（未示出食物制备室和空气移动装置等）示出了用于制备食物的装置的另一示例,该装置在食物制备室的入口开口下方具有空气引导件。</base:FigureReference><base:FigureReference num="0008">图0008示出了用于烹饪食物的装置的另一示例的横截面,该装置在食物烹饪室的入口开口下方的空气移动装置与空气分配区之间具有流动扩散器。</base:FigureReference><base:FigureReference num="0009">图0009示出了烹饪食物的方法的基本步骤。</base:FigureReference></base:Paragraphs>
    </business:DrawingsDescription>
    <business:EmbodimentsDescription>
      <base:Paragraphs num="0052">图1示出了用于烹饪食物的装置10。 例如,设备10是桌面设备。 装置10包括食物制备室12、空气移动装置14、加热装置16和空气引导装置。 应注意,空气引导装置在图1中以虚线18示出,并且与箭头20组合示意性地示出了空气流。 食物制备室12由容器结构22提供,容器结构22至少部分地围绕用于接收待通过热空气流通制备的食物的接收体积24。 接收体积24由上虚线表示。 此外,容器结构22具有侧壁26和底壁28。 侧壁26中的一个和/或底壁28是可透气的并且包括由箭头30指示的空气入口开口,用于热空气进入接收体积中。 应注意,空气入口开口30可以设置在底壁28的整个表面上或在选定区域中。 此外,容器结构具有空气释放开口,如上箭头32所示。 如图1所示,空气释放孔可以由跨越整个上表面的孔提供。 加热装置16被配置成加热由空气移动装置14提供的空气流中的空气。 此外,空气引导装置18提供空气管道装置34,该空气管道装置34从排气开口32经由加热装置16和空气移动装置14到空气入口开口30。</base:Paragraphs>
      <base:Paragraphs num="0053">空气移动装置14是具有空气入口38和空气出口40的风扇36。 风扇36设置于食品烹调室12的侧方。 应注意,根据图1所示的示例,加热装置16设置在食物制备室12的侧面。 然而,可以提供其他布置,例如,如虚线圆圈42所示,其示出了加热装置16在食物制备室12上方的位置。</base:Paragraphs>
      <base:Paragraphs num="0054">根据下面更详细描述的示例,加热装置16布置在从接收体积24不可见的位置。</base:Paragraphs>
      <base:Paragraphs num="0055">外框架结构示出了包围用于烹饪食物的装置的可能的壳体。 当然,壳体可以包括用于将食物填充到食物制备室12中的插入开口,这也将结合下面的其他附图更详细地描述。</base:Paragraphs>
      <base:Paragraphs num="0056">在图2中,设置风扇14作为空气移动装置14,该风扇具有空气吸入侧46和空气吹出侧48。 要注意的是,在空气吸入侧46旁边示出了箭头,表示空气在空气吸入侧被吸入。 在使用中,空气在空气吹送侧以平均吹送方向50吹送。 平均吹出方向50相对于水平和垂直两者具有倾斜角度52。 例如,水平被认为是壳体结构55的水平部分54,并且竖直被认为是壳体结构55的竖直部分56。</base:Paragraphs>
      <base:Paragraphs num="0057">图2A示出了作为离心式风扇58的风扇44的示例,其具有与箭头对准的轴向空气入口方向46和与箭头对准的径向空气出口48。 线60表示旋转轴。</base:Paragraphs>
      <base:Paragraphs num="0058">图2B示出了作为轴流风扇的风扇44,其具有与箭头对齐的轴向空气入口46和与箭头对齐的径向空气出口48。 轴流风扇62具有绕旋转轴64旋转的风扇。 旋转轴64与倾斜角度52同样地,相对于水平及垂直这两者具备倾斜角度。</base:Paragraphs>
      <base:Paragraphs num="0059">在示例中,当食物制备室在使用中时,风扇44设置在食物制备室的侧面。</base:Paragraphs>
      <base:Paragraphs num="0060">图2C示出了呈横流鼓风机或横流风扇66形式的风扇44,其具有围绕旋转轴线68旋转的旋转结构,即垂直于绘图平面的圆柱形结构。</base:Paragraphs>
      <base:Paragraphs num="0061">图3示出了另一示例,其中风扇44是具有轴向空气入口72和径向空气出口74的风扇壳体内部的离心式风扇70。 离心风扇具有绕旋转轴80在旋转面78中旋转的风扇76。 旋转平面78包括相对于水平和垂直两者的倾斜角度,例如角度82。</base:Paragraphs>
      <base:Paragraphs num="0062">离心式风扇提供来自第一方向并远离第二方向的气流的集成引导,其中第二方向与第一方向相差约30°至120°,例如约90°。</base:Paragraphs>
      <base:Paragraphs num="0063">提供倾斜角度,使得来自空气移动装置14的空气流的偏转或引导需要小于90°的量,以便到达食物制备室12下方的区域。 例如,倾斜角度具有在约10°至80°的范围内的相对于水平面的角度。 在示例中,提供在约30°至60°的范围内的角度,例如约45°。</base:Paragraphs>
      <base:Paragraphs num="0064">参考图4A、图4B和图4C,下面描述另一示例性几何关系。 装置10由矩形框架100示出,矩形框架100示出了壳体结构。 此外,象征性地示出了食物制备室12。 此外,第一线102由离心式风扇的旋转轴线限定,这不再进一步示出。 如上所述,第二线104垂直于第一线102布置在旋转平面中。 第三线106垂直于底壁28并延伸穿过底壁28的中心。 第一线102、第二线104和第三线106布置在一个平面中并且形成由第一线102的第一部分110提供的三角形108,第一部分110从第一线102与第二线104的交点延伸到第一线102与第三线106的交点。 三角形108还由第二线104的第二区段112限定,第二区段112从第二线104与第一线102的交点延伸到第二线104与第三线106的交点。 第三线106的第三区段114被定义为三角形108的第三边,第三区段114从第三线106与第一线102的交点延伸到第三线106与第二线104的交点。 三角形108的内圆116布置在设备的壳体结构100内。 第一线和第二线具有布置在壳体结构的高度的中间区域中的交叉点118。 高度由双头箭头120表示。 根据本发明,内圆116具有最大直径122。</base:Paragraphs>
      <base:Paragraphs num="0065">“中间区域”涉及位于高度的中间三分之一处的高度。 高度的中心交叉点的布置允许风扇（例如离心式风扇）的最大直径。</base:Paragraphs>
      <base:Paragraphs num="0066">图4B示出了第一线102、第二线104和第三线106的另一种可能的布置,其中第一线102和第二线104保持彼此垂直,但相对于第三线106一起倾斜,即在顺时针方向上倾斜约10°至30°。 为了更好地理解,第一虚线124指示图4A的第一线102的位置,并且第二虚线126指示图4A的第二线104的位置。 第一线102、第二线104和第三线106形成三角形,但与图4A相比具有不同的比率。 具有最大直径的三角形的内圆由虚线圆128表示。 然而,该内圆128延伸到壳体结构100的外部。 因此,布置在壳体结构100内的三角形的内圆必须较小,如实线圆130所示。</base:Paragraphs>
      <base:Paragraphs num="0067">图4C示出了另一示例,其中彼此垂直的第一线102和第二线104相对于彼此稍微逆时针旋转,导致类似的情况,其中圆130（即,虚线圆）表示三角形的内圆,而实线圆128表示布置在壳体结构100内并作为三角形的内圆的圆的最大直径。</base:Paragraphs>
      <base:Paragraphs num="0068">因此,为了提供具有最大直径的内圆,通过提供相对于水平和垂直两者具有约45°的第一线120和第二线104,应该很好地平衡三角形的角度形成程度。</base:Paragraphs>
      <base:Paragraphs num="0069">图5示出了装置10的另一示例,其中加热装置16布置在从接收体积24不可见的位置。 应当注意,示意性地示出了空气移动装置14。 空气移动装置14可以以不同的变型提供。 此外,必须注意的是,加热装置16也以不同的变型布置,只要从加热装置16到接收体积24的直接视线被排除,即被阻止。</base:Paragraphs>
      <base:Paragraphs num="0070">例如,加热装置16位于食物制备室12的侧面。</base:Paragraphs>
      <base:Paragraphs num="0071">在示例中,空气管道设置在风扇（例如离心式风扇）的出口与底壁中的空气入口开口之间,这也将在下面描述。</base:Paragraphs>
      <base:Paragraphs num="0072">参考图3,将描述一些另外的示例。 如两条线138所示,空气管道装置具有多个引导部分,其中气流方向被改变。 导气部分还由未更详细示出的壳体部分或元件提供,因此它们未用附图标记标记。 为了更好地理解,示出了简化的循环气流140。 例如,离开空气移动装置14的热空气由于引导部分138而略微改变其方向。 此外,气流在底壁28下方改变其方向,如弯曲部分142所示。 然后,气流流过待烹饪的食物,并且在离开食物之后,即在空气释放孔32处,提供方向的进一步改变,如另外的弯曲部分144所示。 在到达侧壁的上部之后,另一弯曲部分146表示另一引导部分。 此外,布置在空气移动装置14内的弯曲部分148示出了提供气流方向的进一步变化。</base:Paragraphs>
      <base:Paragraphs num="0073">根据该示例,第一引导部分（例如,引导部分138）设置在空气置换装置14之后的下游,并且第二引导部分（例如,引导部分146）设置在空气置换装置14之前的上游。 第一引导部分138提供比第二引导部分146更小程度的气流方向变化。</base:Paragraphs>
      <base:Paragraphs num="0074">例如,在空气移动装置（例如,风扇）的吸入侧上提供具有最陡的气流弯曲的引导部分。 在空气置换装置出口附近提供最小的急剧弯曲。</base:Paragraphs>
      <base:Paragraphs num="0075">在示例中,在空气管道装置的所有引导部分中,第二引导部分提供气流方向的最大变化程度,并且第一引导部分提供气流方向的最小变化程度。</base:Paragraphs>
      <base:Paragraphs num="0076">优选地,引导部分提供最小数量的弯曲,以便提供最大气流,即,最小化的气流阻力。 在示例中,空气管道装置包括引导部分,该引导部分提供大约360°的弯曲总和。</base:Paragraphs>
      <base:Paragraphs num="0077">在还结合图3示出的另一示例中,壳体结构100具有用于从上方插入容器结构22的上开口150。 设置盖装置152,例如盖,用于在食物制备期间封闭开口150。 例如,容器结构22被提供为可移除的罐或篮154,其具有用于更容易操作的把手或抓握部分156。</base:Paragraphs>
      <base:Paragraphs num="0078">在也结合图3示出的另一示例中,传感器装置160与空气移动设备14相关联地设置,以检测由空气移动设备14提供的空气流的空气温度。 例如,传感器装置160是布置在空气移动设备14的壳体结构内的传感器。 传感器装置也可以设置在空气出口与容器结构的底壁之间的空气移动装置下游。 传感器可以检测由加热装置加热的空气是否由于例如加热装置的故障而变得过热。</base:Paragraphs>
      <base:Paragraphs num="0079">根据还结合图3示出的另一示例,可移除盘结构170至少部分地设置在食物制备室下方。 例如,食物制备室12至少部分地插入可移除的盘结构170中。 导风管道172设置在可拆卸盘结构170和底壁28之间。 空气引导管道172设置成将加热的空气流从空气出口（例如径向空气出口74）引导到空气入口开口30。 空气引导管道由可拆卸的盘结构和作为物理特征的底壁提供,并且食物制备室与由容器壁限定的空间或区域相关联,容器壁至少部分地围绕食物制备室。</base:Paragraphs>
      <base:Paragraphs num="0080">在示例中,可移除盘结构被提供为一个可移除盘。 在其他示例中,提供两个或更多个可移除盘。</base:Paragraphs>
      <base:Paragraphs num="0081">在另一个示例中,提供了不可移除的盘结构,例如,盘固定到壳体,并且提供了可独立移除的小油和小碎片收集容器。</base:Paragraphs>
      <base:Paragraphs num="0082">尽管图3在一个实施例中示出了上面描述的不同方面,但是应当注意,例如,引导部分的方面、传感器装置的方面、离心式风扇的方面、可拆卸盘结构的方面可以与相应的其他特征组合或没有相应的其他特征（即,以各种不同的组合）来提供。</base:Paragraphs>
      <base:Paragraphs num="0083">在参考示出进一步实施例的以下附图之前,现在将描述本发明的一些一般方面。</base:Paragraphs>
      <base:Paragraphs num="0084">表述“不可见”涉及一种布置,其中加热装置和接收体积（即特别是布置在接收体积中的食物）之间的直接（直线）线是不可能的,因为直接连接线被其它结构阻挡。</base:Paragraphs>
      <base:Paragraphs num="0085">由加热装置提供的热能主要通过热对流传递。 气流将热能输送并传递到待烹饪的食物。 然而,来自加热装置的一些辐射可以例如被盖反射。 然而,这种辐射热形式的所得能量流比对流部分低得多。 例如,加热装置相对于正在烹饪的食物以隐藏的方式布置。 在一个示例中,侧壁相对于接收体积阻挡来自加热装置的辐射热,即,侧壁是加热装置和接收体积之间的直接连接线的屏障。 这避免了食物通过来自加热装置的直接辐射被加热,但是仅通过由所产生的加热空气供应的空气被加热。 然而,可以提供位于食物顶部的反射器,以改善由加热的空气提供给食物的热能的使用。 接收体积不通过来自加热装置的直接辐射接收任何热传递。</base:Paragraphs>
      <base:Paragraphs num="0086">“空气移动装置”也被称为风扇装置或通风装置。 空气移动装置以循环方式提供加热空气的移动,以加热待烹饪的食物。 在一个示例中,空气移动装置在不改变其他空气参数的情况下提供空气移动。 在其他示例中,空气移动设备还提供影响或调节其他空气特性/参数,例如湿度、氧含量、再利用空气与新鲜空气输入的比率。 加热的空气可以被供应到具有不同插入温度的食物。 例如,当将加热的空气施加到冷冻炸物时,由加热器供应到待加热的空气的热能几乎完全传递到冷冻炸物,使得所得到的空气流至少在第一时间段内（例如,在前10至30秒内）可以处于低于0℃的温度。 在食物制备过程结束时,空气温度可以达到140℃至200℃或更高。 空气温度可以是可调节的,这取决于食物的类型。</base:Paragraphs>
      <base:Paragraphs num="0087">容器结构可以通过提供底壁和周向连续侧壁或多个侧壁而以锅或面包的形式部分地围绕食物制备室。</base:Paragraphs>
      <base:Paragraphs num="0088">容器结构可以通过不仅提供底壁和侧壁而且还提供封闭的上部结构（诸如盖或罩）来以封闭的锅或面包的形式完全包围食物制备室。</base:Paragraphs>
      <base:Paragraphs num="0089">在每种情况下,采取措施以允许加热的空气流进入食物制备室,即通过空气入口开口,并且还允许空气离开食物制备室,即通过空气排出开口。</base:Paragraphs>
      <base:Paragraphs num="0090">与气流相关的“开口”的表述涉及空气通过的能力。 这可以例如通过筛网、网格或网格状结构来提供。 表述“加热的空气”涉及在食物制备过程结束时或在温度峰值处被加热到约80℃至200℃的温度范围的空气。 空气可以包括不同量的相对湿度。 例如,可以提供5%至100%的相对湿度范围。</base:Paragraphs>
      <base:Paragraphs num="0091">表述“食物制备室的侧面”是指空气移位装置在水平方向上在食物制备室的侧面或侧面的布置。 例如,空气移动装置位于食物制备室的侧壁旁边。 空气移动装置也可以在水平方向上侧向定位并且可以向上移动,使得空气移动装置在容器结构上方延伸。</base:Paragraphs>
      <base:Paragraphs num="0092">术语“水平”在正常操作中涉及水平平面或轴线。 术语“垂直”涉及相应的垂直平面或轴。</base:Paragraphs>
      <base:Paragraphs num="0093">例如,术语水平涉及例如厨房的工作表面或工作表面。 在其他示例中,术语“垂直”涉及垂直于水平的线。</base:Paragraphs>
      <base:Paragraphs num="0094">例如,空气释放开口32由容器结构22的侧壁部分提供。</base:Paragraphs>
      <base:Paragraphs num="0095">在示例中,排放开口32被设置为在容器结构22上方定向的开口。 在其他示例中,排放开口32由容器结构22的侧壁部分提供。</base:Paragraphs>
      <base:Paragraphs num="0096">术语“底壁”是指设置在下部中的在正常操作状态下向下指向的壁区段或壁区域。 术语“侧壁”还表示具有连续的侧壁或多个侧壁段的侧壁布置。</base:Paragraphs>
      <base:Paragraphs num="0097">关于离心式风扇,表述“轴向空气入口”涉及空气移动装置的空气入口或抽吸开口,例如设置在离心式风扇的旋转轴线附近或设置在轴流式风扇的旋转轴线附近。 在离心式风扇的情况下,空气入口可以设置在旋转轴线与由离心式风扇的旋转叶片（或叶片）描绘的外周边之间。</base:Paragraphs>
      <base:Paragraphs num="0098">在示例中,空气移动装置设置在加热装置的下游。 在其他示例中,加热装置设置在空气移动装置的下游。 在另一示例中,在空气移动设备的上游和下游提供加热。</base:Paragraphs>
      <base:Paragraphs num="0099">如上所述,空气出口可以设置为径向空气出口。 然而,空气也可以以切向运动分量吹出。 在示例中,接收体积24是食物制备室12的子体积（即,体积的一部分）。</base:Paragraphs>
      <base:Paragraphs num="0100">空气移动装置14的倾斜布置提供了以下效果：空气流的循环部分包括空气管道或空气路径的最小程度的弯曲,其中最陡的弯曲位于风扇的空气入口处。 这意味着气流的阻力最小化,因此提高了空气流速。</base:Paragraphs>
      <base:Paragraphs num="0101">图6示出了另一示例,其中具有收集体积182的收集装置180设置在食物制备室12下方以收集残余物。 术语“残余物”是指例如油和碎片。</base:Paragraphs>
      <base:Paragraphs num="0102">在另一示例中,空气引导元件184被设置成将容器结构22下方的水平气流186在向上方向上朝向空气入口开口30引导。 收集装置180在背离水平气流186的一侧188上布置在空气引导元件184的侧面。</base:Paragraphs>
      <base:Paragraphs num="0103">收集装置180布置在空气引导元件的下游,即,空气引导元件提供对加热的空气流的屏蔽。 在示例中,收集装置由可移除或可移除的盘的至少一个凹部提供。</base:Paragraphs>
      <base:Paragraphs num="0104">在示例中,可移除盘包括排放开口,并且可移除收集容器设置在开口下方（未进一步示出）。</base:Paragraphs>
      <base:Paragraphs num="0105">在另一个示例中,收集装置被提供为安装在可移除盘的凹部中的独立嵌件（也未进一步示出）。</base:Paragraphs>
      <base:Paragraphs num="0106">图7在图7A中以横截面示出了另一示例,并且在图7B中以透视图示出了另一示例。 空气分配管道190设置在底壁28中的空气入口开口30下方。 空气引导件192被设置为位于空气分配管道190的下表面194上在空气入口开口30下方的脊。 例如,脊部在空气分配管道190的横截面上延伸。 在示例中,脊部在横截面的至少三分之一上延伸,例如在一个区段中或甚至在远端区段中延伸。 在另一示例中,脊部在横截面的至少一半上延伸。 在另一示例中,脊部在整个横截面上延伸。 例如,如图所示,脊部在横截面的整个宽度上延伸,如图7B所示。 空气引导件192以倾斜的方式布置,并且以第一虚线198所示的直线的延伸与空气分配管道的一般或平均方向的法线（或直角）之间的角度196示出,该法线由第二虚线200示出。 空气引导件以相对于空气出口的吹出方向的垂直方向倾斜的方式布置在空气入口开口30下方,使得提供均匀分布的空气流。 这由箭头202示出,箭头202示出了图7B中的三个气流。</base:Paragraphs>
      <base:Paragraphs num="0107">“倾斜方式”涉及吹出方向相对于竖直方向的至少5°或10°的角度。 “吹出方向”与吹出气流的中心气流方向相关。</base:Paragraphs>
      <base:Paragraphs num="0108">如上所述,脊可以在宽度的整个横截面上延伸,或者甚至仅在宽度的一部分上延伸。 此外,如图所示,空气引导件192可以设置为直线空气引导件。 在其他示例（未示出）中,空气引导件以弯曲的方式提供。</base:Paragraphs>
      <base:Paragraphs num="0109">图8示出了另一示例,其中,气流扩散器210设置在空气置换装置14的空气出口212与设置在底壁28的空气入口开口30下方的空气分配区域214之间。 流扩散器被设置为管道段216,该管道段216具有横向于空气通过方向的减小的横截面,如双箭头218所示,以补偿空气出口的不对称空气输出。 流扩散器设置为空气管道的倾斜壁。 例如,底壁区段相对于水平面倾斜。 在示例中,在管道段216中提供唇缘结构。 例如,倾斜壁具有比旋转面相对于水平的倾斜角度小的相对于水平的倾斜角度。 例如,第一角度220表示旋转平面相对于水平面的角度,并且第二角度222表示倾斜壁（例如,壁区段224）相对于水平面的角度。 可以看出,第二角度小于第一角度。</base:Paragraphs>
      <base:Paragraphs num="0110">图9示出了用于烹饪食物的方法300的示例,例如在桌面设备上,并且包括以下步骤。 在第一步骤302中,将食物供应到食物制备室,所述食物制备室由容器结构提供,所述容器结构至少部分地包围用于接收待制备的食物的接收体积。 在第二步骤304中,向食物制备室提供热空气的流通流。 热空气的流通流由空气移动装置和加热装置提供。 循环空气流由空气引导装置提供,该空气引导装置提供空气管道装置,该空气管道装置从容器结构的排放开口经由加热装置和空气移位装置到容器结构的空气入口开口。</base:Paragraphs>
      <base:Paragraphs num="0111">为了使空气运动,设置有具有空气入口和空气出口的风扇,该风扇设置在食物制备室的侧面。</base:Paragraphs>
      <base:Paragraphs num="0112">第一步骤302也被称为步骤a）,并且第二步骤304也被称为步骤b）。</base:Paragraphs>
      <base:Paragraphs num="0113">在另一示例中,空气由加热装置加热,该加热装置布置在从接收体积不可见的位置。</base:Paragraphs>
      <base:Paragraphs num="0114">应当注意,结合不同实施例的上述特征提供了该方法的其他示例。</base:Paragraphs>
      <base:Paragraphs num="0115">应当注意,已经参考不同的主题描述了本发明的实施例。 具体地,参考方法类型权利要求描述了一些实施例,而参考设备类型权利要求描述了其他实施例。 然而,本领域技术人员将从前面的描述和下面的描述中推断出,除非另有说明,否则除了属于一种类型的主题的特征的组合之外,涉及不同主题的特征之间的任何组合也被认为在本申请中公开。 然而,可以组合所有特征以提供超过这些特征的简单总和的协同效应。</base:Paragraphs>
      <base:Paragraphs num="0116">在附图和上述说明中详细地例示和说明了本发明,但该例示和说明是例示性的,不应被限定性地解释。 本发明不限于所公开的实施例。 通过研究附图、公开内容和所附权利要求,本领域技术人员在实践所要求保护的发明时可以理解和实现所公开的实施例的其他变型。</base:Paragraphs>
      <base:Paragraphs num="0117">在权利要求中,词语“包括”不排除其他元件或步骤,并且不定冠词“一”或“一个”不排除多个。 单个处理器或其他单元可以实现权利要求中记载的若干项的功能。 在相互不同的从属权利要求中记载的某些措施并不指示不能有利地使用这些措施的组合。 权利要求中的任何附图标记不应被解释为限制范围。</base:Paragraphs>
    </business:EmbodimentsDescription>
  </business:Description>
  <business:Drawings lang="ja" sourceDB="JP">
    <base:Figure num="0001">
      <base:Image id="000003" he="47" wi="63" file="2016519992_000003.TIF" imgContent="drawing" imgFormat="TIFF"/>
    </base:Figure>
    <base:Figure num="0002">
      <base:Image id="000004" he="36" wi="63" file="2016519992_000004.TIF" imgContent="drawing" imgFormat="TIFF"/>
    </base:Figure>
    <base:Figure num="0003">
      <base:Image id="000005" he="35" wi="63" file="2016519992_000005.TIF" imgContent="drawing" imgFormat="TIFF"/>
    </base:Figure>
    <base:Figure num="0004">
      <base:Image id="000006" he="35" wi="63" file="2016519992_000006.TIF" imgContent="drawing" imgFormat="TIFF"/>
    </base:Figure>
    <base:Figure num="0005">
      <base:Image id="000007" he="54" wi="68" file="2016519992_000007.TIF" imgContent="drawing" imgFormat="TIFF"/>
    </base:Figure>
    <base:Figure num="0006">
      <base:Image id="000008" he="49" wi="44" file="2016519992_000008.TIF" imgContent="drawing" imgFormat="TIFF"/>
    </base:Figure>
    <base:Figure num="0007">
      <base:Image id="000009" he="103" wi="68" file="2016519992_000009.TIF" imgContent="drawing" imgFormat="TIFF"/>
    </base:Figure>
    <base:Figure num="0008">
      <base:Image id="000010" he="62" wi="33" file="2016519992_000010.TIF" imgContent="drawing" imgFormat="TIFF"/>
    </base:Figure>
    <base:Figure num="0009">
      <base:Image id="000011" he="29" wi="47" file="2016519992_000011.TIF" imgContent="drawing" imgFormat="TIFF"/>
    </base:Figure>
    <base:Figure num="0010">
      <base:Image id="000012" he="43" wi="58" file="2016519992_000012.TIF" imgContent="drawing" imgFormat="TIFF"/>
    </base:Figure>
    <base:Figure num="0011">
      <base:Image id="000013" he="38" wi="57" file="2016519992_000013.TIF" imgContent="drawing" imgFormat="TIFF"/>
    </base:Figure>
    <base:Figure num="0012">
      <base:Image id="000014" he="55" wi="47" file="2016519992_000014.TIF" imgContent="drawing" imgFormat="TIFF"/>
    </base:Figure>
    <base:Figure num="0013">
      <base:Image id="000015" he="44" wi="63" file="2016519992_000015.TIF" imgContent="drawing" imgFormat="TIFF"/>
    </base:Figure>
    <base:Figure num="0014">
      <base:Image id="000016" he="38" wi="44" file="2016519992_000016.TIF" imgContent="drawing" imgFormat="TIFF"/>
    </base:Figure>
  </business:Drawings>
  <business:Claims lang="ja" dataFormat="original" sourceDB="JP">
    <business:Claim num="0001">
      <business:ClaimText>一种用于烹饪食物的装置,包括： -食物制备室, -空气移动装置, -加热装置, -空气引导装置, 所述食物制备室包括： -容器结构,所述容器结构至少部分地围绕接收体积,所述接收体积用于接收待通过热空气的流通流烹饪的食物, 其中,所述容器结构具有侧壁和底壁,所述侧壁中的一个和/或所述底壁是可透气的并且包括用于热空气进入所述接收体积中的空气入口开口,所述容器结构具有空气释放开口,所述加热装置适于加热由所述空气置换装置供应的空气流中的空气,所述空气引导装置提供从所述释放开口经由所述加热装置和所述空气置换装置到所述空气入口开口的空气管道装置,所述空气置换装置是具有空气入口和空气出口的风扇,所述风扇设置在所述食物制备室的侧面。</business:ClaimText>
    </business:Claim>
    <business:Claim num="0002">
      <business:ClaimText>根据权利要求1所述的装置,其中,作为所述空气移动装置,设置有具有空气吸入侧和空气吹出侧的所述风扇,在使用中,所述空气以平均吹出方向在所述空气吹出侧吹出,所述平均吹出方向相对于水平和垂直这两者具备倾斜角。</business:ClaimText>
    </business:Claim>
    <business:Claim num="0003">
      <business:ClaimText>根据权利要求1或2所述的装置,其中,所述风扇是在具有轴向空气入口和径向空气出口的风扇壳体内部的离心式风扇,所述离心式风扇具有在旋转平面中旋转的叶片,所述旋转平面相对于水平方向和垂直方向都具有倾斜角度。</business:ClaimText>
    </business:Claim>
    <business:Claim num="0004">
      <business:ClaimText>根据权利要求2或3所述的装置,其中,所述倾斜角包括在约10°至80°的范围内的相对于水平的角度。</business:ClaimText>
    </business:Claim>
    <business:Claim num="0005">
      <business:ClaimText>根据权利要求1至4中任一项所述的装置,其中,所述第一线由旋转轴线限定,所述第二线在所述旋转平面中垂直于所述第一线布置,所述第三线垂直于所述底壁并且穿过所述底壁的中心,所述第一线、所述第二线和所述第三线布置在一个平面中并且形成三角形,所述三角形的内圆布置在所述装置的壳体结构的内部,所述第一线和所述第二线具有布置在所述壳体结构的高度的中间区域中的交叉点,所述内圆具有最大直径。</business:ClaimText>
    </business:Claim>
    <business:Claim num="0006">
      <business:ClaimText>根据权利要求1至5中任一项所述的设备,其中,所述设备是台式设备。</business:ClaimText>
    </business:Claim>
    <business:Claim num="0007">
      <business:ClaimText>根据权利要求1至6中任一项所述的装置,其中,所述加热装置布置在从所述接收体积不可见的位置。</business:ClaimText>
    </business:Claim>
    <business:Claim num="0008">
      <business:ClaimText>根据权利要求1至7中任一项所述的装置,其中,所述加热装置位于所述食物制备室的侧面。</business:ClaimText>
    </business:Claim>
    <business:Claim num="0009">
      <business:ClaimText>根据权利要求1至8中任一项所述的装置,其中,所述空气管道装置具有多个引导部分,在所述多个引导部分中,空气流方向改变,第一引导部分设置在所述空气置换装置的下游之后,并且第二引导部分设置在所述空气置换装置的上游之前,所述第一引导部分提供比所述第二引导部分更小的空气流方向变化。</business:ClaimText>
    </business:Claim>
    <business:Claim num="0010">
      <business:ClaimText>根据权利要求1至9中任一项所述的设备,其中,与所述空气移动装置相关联地设置有传感器装置,用于检测由所述空气移动装置提供的空气流的空气温度。</business:ClaimText>
    </business:Claim>
    <business:Claim num="0011">
      <business:ClaimText>根据权利要求1至10中任一项所述的装置,其中,可移除的盘结构至少部分地设置在所述食物制备室的下方,所述可移除的盘结构与所述底壁之间的空气引导管道由所述可移除的盘结构提供,用于将加热的空气流从所述空气出口引导到所述空气入口开口,和/或具有收集体积的收集装置设置在所述食物制备室的下方,用于收集残余物。</business:ClaimText>
    </business:Claim>
    <business:Claim num="0012">
      <business:ClaimText>根据权利要求11所述的装置,其中,设置有空气引导元件,所述空气引导元件将所述容器结构下方的水平气流在向上方向上朝向所述空气入口开口引导,并且其中,所述收集装置在背离所述水平气流的一侧上布置在所述空气引导元件的旁边。</business:ClaimText>
    </business:Claim>
    <business:Claim num="0013">
      <business:ClaimText>根据权利要求1至12中任一项所述的装置,其中,空气分配管道设置在所述底壁中的所述空气入口开口下方,并且空气引导件设置为在所述空气入口开口下方布置在所述空气分配管道的下表面上的脊部,所述空气引导件以相对于所述空气出口的吹出方向的垂直方向倾斜的方式布置,以便在所述空气入口开口下方提供均匀分配的空气流。</business:ClaimText>
    </business:Claim>
    <business:Claim num="0014">
      <business:ClaimText>根据权利要求1至13中任一项所述的装置,其中,在所述空气出口与设置在所述底壁的所述空气入口开口下方的空气分配区域之间设置气流扩散器,所述气流扩散器设置为具有横向于空气通过方向的减小的横截面的管道段,以补偿所述空气出口的不对称空气输出。</business:ClaimText>
    </business:Claim>
    <business:Claim num="0015">
      <business:ClaimText>a）将食物供应到食物制备室,所述食物制备室由容器结构提供,所述容器结构至少部分地包围用于接收待制备的食物的接收体积,b）将热空气的流通流供应到所述食物制备室,所述热空气的流通流由空气移动装置和加热装置提供,循环空气流由空气引导装置提供,所述空气引导装置提供空气管道装置,所述空气管道装置从所述容器结构的排放开口经由所述加热装置和所述空气移动装置到所述容器结构的空气入口开口,其中,设置有用于空气移动的具有空气入口和空气出口的风扇,所述风扇设置在所述食物制备室的侧面。</business:ClaimText>
    </business:Claim>
  </business:Claims>
  <business:SearchReportData id="searchreportdata000001">
    <business:ExternalSearchReport id="externalsearchreport000017" file="2016519992_000017.TIF" lang="ja" height="241" width="170" imageFormat="TIFF"/>
  </business:SearchReportData>
  <business:SearchReportData id="searchreportdata000002">
    <business:ExternalSearchReport id="externalsearchreport000018" file="2016519992_000018.TIF" lang="ja" height="241" width="170" imageFormat="TIFF"/>
  </business:SearchReportData>
  <business:SearchReportData id="searchreportdata000003">
    <business:ExternalSearchReport id="externalsearchreport000019" file="2016519992_000019.TIF" lang="ja" height="241" width="170" imageFormat="TIFF"/>
  </business:SearchReportData>
</business:PatentDocumentAndRelated>